Workbook

Sheet SFF（全体予算）
A1: 項目
A2: 売上 | B2: 売上80％ | C2: 前年度参考予想 | D2: 売上120％
A3: 出場費 | B3: ='SFF①（日野市民会館）'!D3+'SFF②（パピヨン24ガスホール）'!D3+'SFF③（大阪国際交流センター）'!D3+'SFF④（青葉の森公園芸術文化ホール） '!D3+'SFF⑤（松田町生涯学習センター） '!D3+'SFF⑥（ALL草加市文化会館）'!D3 -> 4240000 | C3: ='SFF①（日野市民会館）'!E3+'SFF②（パピヨン24ガスホール）'!E3+'SFF③（大阪国際交流センター）'!E3+'SFF④（青葉の森公園芸術文化ホール） '!E3+'SFF⑤（松田町生涯学習センター） '!E3+'SFF⑥（ALL草加市文化会館）'!E3 -> 5300000 | D3: ='SFF①（日野市民会館）'!F3+'SFF②（パピヨン24ガスホール）'!F3+'SFF③（大阪国際交流センター）'!F3+'SFF④（青葉の森公園芸術文化ホール） '!F3+'SFF⑤（松田町生涯学習センター） '!F3+'SFF⑥（ALL草加市文化会館）'!F3 -> 6360000
A4: 客席代 | B4: ='SFF①（日野市民会館）'!D4+'SFF②（パピヨン24ガスホール）'!D4+'SFF③（大阪国際交流センター）'!D4+'SFF④（青葉の森公園芸術文化ホール） '!D4+'SFF⑤（松田町生涯学習センター） '!D4+'SFF⑥（ALL草加市文化会館）'!D4 -> 19295584 | C4: ='SFF①（日野市民会館）'!E4+'SFF②（パピヨン24ガスホール）'!E4+'SFF③（大阪国際交流センター）'!E4+'SFF④（青葉の森公園芸術文化ホール） '!E4+'SFF⑤（松田町生涯学習センター） '!E4+'SFF⑥（ALL草加市文化会館）'!E4 -> 24119480 | D4: ='SFF①（日野市民会館）'!F4+'SFF②（パピヨン24ガスホール）'!F4+'SFF③（大阪国際交流センター）'!F4+'SFF④（青葉の森公園芸術文化ホール） '!F4+'SFF⑤（松田町生涯学習センター） '!F4+'SFF⑥（ALL草加市文化会館）'!F4 -> 28943376
A5: バックサポート代 | B5: ='SFF①（日野市民会館）'!D5+'SFF②（パピヨン24ガスホール）'!D5+'SFF③（大阪国際交流センター）'!D5+'SFF④（青葉の森公園芸術文化ホール） '!D5+'SFF⑤（松田町生涯学習センター） '!D5+'SFF⑥（ALL草加市文化会館）'!D5 -> 1161600 | C5: ='SFF①（日野市民会館）'!E5+'SFF②（パピヨン24ガスホール）'!E5+'SFF③（大阪国際交流センター）'!E5+'SFF④（青葉の森公園芸術文化ホール） '!E5+'SFF⑤（松田町生涯学習センター） '!E5+'SFF⑥（ALL草加市文化会館）'!E5 -> 1452000 | D5: ='SFF①（日野市民会館）'!F5+'SFF②（パピヨン24ガスホール）'!F5+'SFF③（大阪国際交流センター）'!F5+'SFF④（青葉の森公園芸術文化ホール） '!F5+'SFF⑤（松田町生涯学習センター） '!F5+'SFF⑥（ALL草加市文化会館）'!F5 -> 1742400
A6: カラーリング代 | B6: ='SFF①（日野市民会館）'!D6+'SFF②（パピヨン24ガスホール）'!D6+'SFF③（大阪国際交流センター）'!D6+'SFF④（青葉の森公園芸術文化ホール） '!D6+'SFF⑤（松田町生涯学習センター） '!D6+'SFF⑥（ALL草加市文化会館）'!D6 -> 1056000 | C6: ='SFF①（日野市民会館）'!E6+'SFF②（パピヨン24ガスホール）'!E6+'SFF③（大阪国際交流センター）'!E6+'SFF④（青葉の森公園芸術文化ホール） '!E6+'SFF⑤（松田町生涯学習センター） '!E6+'SFF⑥（ALL草加市文化会館）'!E6 -> 1320000 | D6: ='SFF①（日野市民会館）'!F6+'SFF②（パピヨン24ガスホール）'!F6+'SFF③（大阪国際交流センター）'!F6+'SFF④（青葉の森公園芸術文化ホール） '!F6+'SFF⑤（松田町生涯学習センター） '!F6+'SFF⑥（ALL草加市文化会館）'!F6 -> 1584000
A7: アパレル売上 | B7: ='SFF①（日野市民会館）'!D7+'SFF②（パピヨン24ガスホール）'!D7+'SFF③（大阪国際交流センター）'!D7+'SFF④（青葉の森公園芸術文化ホール） '!D7+'SFF⑤（松田町生涯学習センター） '!D7+'SFF⑥（ALL草加市文化会館）'!D7 -> 928000 | C7: ='SFF①（日野市民会館）'!E7+'SFF②（パピヨン24ガスホール）'!E7+'SFF③（大阪国際交流センター）'!E7+'SFF④（青葉の森公園芸術文化ホール） '!E7+'SFF⑤（松田町生涯学習センター） '!E7+'SFF⑥（ALL草加市文化会館）'!E7 -> 1160000 | D7: ='SFF①（日野市民会館）'!F7+'SFF②（パピヨン24ガスホール）'!F7+'SFF③（大阪国際交流センター）'!F7+'SFF④（青葉の森公園芸術文化ホール） '!F7+'SFF⑤（松田町生涯学習センター） '!F7+'SFF⑥（ALL草加市文化会館）'!F7 -> 1392000
A8: 写真売上 | B8: ='SFF①（日野市民会館）'!D8+'SFF②（パピヨン24ガスホール）'!D8+'SFF③（大阪国際交流センター）'!D8+'SFF④（青葉の森公園芸術文化ホール） '!D8+'SFF⑤（松田町生涯学習センター） '!D8+'SFF⑥（ALL草加市文化会館）'!D8 -> 2256000 | C8: ='SFF①（日野市民会館）'!E8+'SFF②（パピヨン24ガスホール）'!E8+'SFF③（大阪国際交流センター）'!E8+'SFF④（青葉の森公園芸術文化ホール） '!E8+'SFF⑤（松田町生涯学習センター） '!E8+'SFF⑥（ALL草加市文化会館）'!E8 -> 2820000 | D8: ='SFF①（日野市民会館）'!F8+'SFF②（パピヨン24ガスホール）'!F8+'SFF③（大阪国際交流センター）'!F8+'SFF④（青葉の森公園芸術文化ホール） '!F8+'SFF⑤（松田町生涯学習センター） '!F8+'SFF⑥（ALL草加市文化会館）'!F8 -> 3384000
A9: 動画販売 | B9: ='SFF①（日野市民会館）'!D9+'SFF②（パピヨン24ガスホール）'!D9+'SFF③（大阪国際交流センター）'!D9+'SFF④（青葉の森公園芸術文化ホール） '!D9+'SFF⑤（松田町生涯学習センター） '!D9+'SFF⑥（ALL草加市文化会館）'!D9 -> 720000 | C9: ='SFF①（日野市民会館）'!E9+'SFF②（パピヨン24ガスホール）'!E9+'SFF③（大阪国際交流センター）'!E9+'SFF④（青葉の森公園芸術文化ホール） '!E9+'SFF⑤（松田町生涯学習センター） '!E9+'SFF⑥（ALL草加市文化会館）'!E9 -> 900000 | D9: ='SFF①（日野市民会館）'!F9+'SFF②（パピヨン24ガスホール）'!F9+'SFF③（大阪国際交流センター）'!F9+'SFF④（青葉の森公園芸術文化ホール） '!F9+'SFF⑤（松田町生涯学習センター） '!F9+'SFF⑥（ALL草加市文化会館）'!F9 -> 1080000
A10: 協賛金 | B10: ='SFF①（日野市民会館）'!D10+'SFF②（パピヨン24ガスホール）'!D10+'SFF③（大阪国際交流センター）'!D10+'SFF④（青葉の森公園芸術文化ホール） '!D10+'SFF⑤（松田町生涯学習センター） '!D10+'SFF⑥（ALL草加市文化会館）'!D10 -> 8170000 | C10: ='SFF①（日野市民会館）'!E10+'SFF②（パピヨン24ガスホール）'!E10+'SFF③（大阪国際交流センター）'!E10+'SFF④（青葉の森公園芸術文化ホール） '!E10+'SFF⑤（松田町生涯学習センター） '!E10+'SFF⑥（ALL草加市文化会館）'!E10 -> 8170000 | D10: ='SFF①（日野市民会館）'!F10+'SFF②（パピヨン24ガスホール）'!F10+'SFF③（大阪国際交流センター）'!F10+'SFF④（青葉の森公園芸術文化ホール） '!F10+'SFF⑤（松田町生涯学習センター） '!F10+'SFF⑥（ALL草加市文化会館）'!F10 -> 11900000
A11: 売上合計 | B11: =SUM(B3:B10) -> 37827184 | C11: =SUM(C3:C10) -> 45241480 | D11: =SUM(D3:D10) -> 56385776
A12: 経費
A13: 出場チケット手数料（3.6%) | B13: ='SFF①（日野市民会館）'!D13+'SFF②（パピヨン24ガスホール）'!D13+'SFF③（大阪国際交流センター）'!D13+'SFF④（青葉の森公園芸術文化ホール） '!D13+'SFF⑤（松田町生涯学習センター） '!D13+'SFF⑥（ALL草加市文化会館）'!D13 -> 152640 | C13: ='SFF①（日野市民会館）'!E13+'SFF②（パピヨン24ガスホール）'!E13+'SFF③（大阪国際交流センター）'!E13+'SFF④（青葉の森公園芸術文化ホール） '!E13+'SFF⑤（松田町生涯学習センター） '!E13+'SFF⑥（ALL草加市文化会館）'!E13 -> 190800 | D13: ='SFF①（日野市民会館）'!F13+'SFF②（パピヨン24ガスホール）'!F13+'SFF③（大阪国際交流センター）'!F13+'SFF④（青葉の森公園芸術文化ホール） '!F13+'SFF⑤（松田町生涯学習センター） '!F13+'SFF⑥（ALL草加市文化会館）'!F13 -> 228960
A14: 客席チケット手数料（3.6%) | B14: ='SFF①（日野市民会館）'!D14+'SFF②（パピヨン24ガスホール）'!D14+'SFF③（大阪国際交流センター）'!D14+'SFF④（青葉の森公園芸術文化ホール） '!D14+'SFF⑤（松田町生涯学習センター） '!D14+'SFF⑥（ALL草加市文化会館）'!D14 -> 694641.02 | C14: ='SFF①（日野市民会館）'!E14+'SFF②（パピヨン24ガスホール）'!E14+'SFF③（大阪国際交流センター）'!E14+'SFF④（青葉の森公園芸術文化ホール） '!E14+'SFF⑤（松田町生涯学習センター） '!E14+'SFF⑥（ALL草加市文化会館）'!E14 -> 868301.28 | D14: ='SFF①（日野市民会館）'!F14+'SFF②（パピヨン24ガスホール）'!F14+'SFF③（大阪国際交流センター）'!F14+'SFF④（青葉の森公園芸術文化ホール） '!F14+'SFF⑤（松田町生涯学習センター） '!F14+'SFF⑥（ALL草加市文化会館）'!F14 -> 1041961.5
A15: バックサポートチケット手数料（3.6%) | B15: ='SFF①（日野市民会館）'!D15+'SFF②（パピヨン24ガスホール）'!D15+'SFF③（大阪国際交流センター）'!D15+'SFF④（青葉の森公園芸術文化ホール） '!D15+'SFF⑤（松田町生涯学習センター） '!D15+'SFF⑥（ALL草加市文化会館）'!D15 -> 41817.6 | C15: ='SFF①（日野市民会館）'!E15+'SFF②（パピヨン24ガスホール）'!E15+'SFF③（大阪国際交流センター）'!E15+'SFF④（青葉の森公園芸術文化ホール） '!E15+'SFF⑤（松田町生涯学習センター） '!E15+'SFF⑥（ALL草加市文化会館）'!E15 -> 52272 | D15: ='SFF①（日野市民会館）'!F15+'SFF②（パピヨン24ガスホール）'!F15+'SFF③（大阪国際交流センター）'!F15+'SFF④（青葉の森公園芸術文化ホール） '!F15+'SFF⑤（松田町生涯学習センター） '!F15+'SFF⑥（ALL草加市文化会館）'!F15 -> 62726.4
A16: カラーリングチケット手数料（3.2%） | B16: ='SFF①（日野市民会館）'!D16+'SFF②（パピヨン24ガスホール）'!D16+'SFF③（大阪国際交流センター）'!D16+'SFF④（青葉の森公園芸術文化ホール） '!D16+'SFF⑤（松田町生涯学習センター） '!D16+'SFF⑥（ALL草加市文化会館）'!D16 -> 0 | C16: ='SFF①（日野市民会館）'!E16+'SFF②（パピヨン24ガスホール）'!E16+'SFF③（大阪国際交流センター）'!E16+'SFF④（青葉の森公園芸術文化ホール） '!E16+'SFF⑤（松田町生涯学習センター） '!E16+'SFF⑥（ALL草加市文化会館）'!E16 -> 0 | D16: ='SFF①（日野市民会館）'!F16+'SFF②（パピヨン24ガスホール）'!F16+'SFF③（大阪国際交流センター）'!F16+'SFF④（青葉の森公園芸術文化ホール） '!F16+'SFF⑤（松田町生涯学習センター） '!F16+'SFF⑥（ALL草加市文化会館）'!F16 -> 0
A17: 動画手数料（3.6%） | B17: ='SFF①（日野市民会館）'!D17+'SFF②（パピヨン24ガスホール）'!D17+'SFF③（大阪国際交流センター）'!D17+'SFF④（青葉の森公園芸術文化ホール） '!D17+'SFF⑤（松田町生涯学習センター） '!D17+'SFF⑥（ALL草加市文化会館）'!D17 -> 25920 | C17: ='SFF①（日野市民会館）'!E17+'SFF②（パピヨン24ガスホール）'!E17+'SFF③（大阪国際交流センター）'!E17+'SFF④（青葉の森公園芸術文化ホール） '!E17+'SFF⑤（松田町生涯学習センター） '!E17+'SFF⑥（ALL草加市文化会館）'!E17 -> 32400 | D17: ='SFF①（日野市民会館）'!F17+'SFF②（パピヨン24ガスホール）'!F17+'SFF③（大阪国際交流センター）'!F17+'SFF④（青葉の森公園芸術文化ホール） '!F17+'SFF⑤（松田町生涯学習センター） '!F17+'SFF⑥（ALL草加市文化会館）'!F17 -> 38880
A18: アパレル仕入れ | B18: ='SFF①（日野市民会館）'!D18+'SFF②（パピヨン24ガスホール）'!D18+'SFF③（大阪国際交流センター）'!D18+'SFF④（青葉の森公園芸術文化ホール） '!D18+'SFF⑤（松田町生涯学習センター） '!D18+'SFF⑥（ALL草加市文化会館）'!D18 -> 1400000 | C18: ='SFF①（日野市民会館）'!E18+'SFF②（パピヨン24ガスホール）'!E18+'SFF③（大阪国際交流センター）'!E18+'SFF④（青葉の森公園芸術文化ホール） '!E18+'SFF⑤（松田町生涯学習センター） '!E18+'SFF⑥（ALL草加市文化会館）'!E18 -> 1400000 | D18: ='SFF①（日野市民会館）'!F18+'SFF②（パピヨン24ガスホール）'!F18+'SFF③（大阪国際交流センター）'!F18+'SFF④（青葉の森公園芸術文化ホール） '!F18+'SFF⑤（松田町生涯学習センター） '!F18+'SFF⑥（ALL草加市文化会館）'!F18 -> 1400000
A19: 演出費 | B19: ='SFF①（日野市民会館）'!D19+'SFF②（パピヨン24ガスホール）'!D19+'SFF③（大阪国際交流センター）'!D19+'SFF④（青葉の森公園芸術文化ホール） '!D19+'SFF⑤（松田町生涯学習センター） '!D19+'SFF⑥（ALL草加市文化会館）'!D19 -> 7909300 | C19: ='SFF①（日野市民会館）'!E19+'SFF②（パピヨン24ガスホール）'!E19+'SFF③（大阪国際交流センター）'!E19+'SFF④（青葉の森公園芸術文化ホール） '!E19+'SFF⑤（松田町生涯学習センター） '!E19+'SFF⑥（ALL草加市文化会館）'!E19 -> 7909300 | D19: ='SFF①（日野市民会館）'!F19+'SFF②（パピヨン24ガスホール）'!F19+'SFF③（大阪国際交流センター）'!F19+'SFF④（青葉の森公園芸術文化ホール） '!F19+'SFF⑤（松田町生涯学習センター） '!F19+'SFF⑥（ALL草加市文化会館）'!F19 -> 7909300
A20: 人件費（審査員） | B20: ='SFF①（日野市民会館）'!D20+'SFF②（パピヨン24ガスホール）'!D20+'SFF③（大阪国際交流センター）'!D20+'SFF④（青葉の森公園芸術文化ホール） '!D20+'SFF⑤（松田町生涯学習センター） '!D20+'SFF⑥（ALL草加市文化会館）'!D20 -> 300000 | C20: ='SFF①（日野市民会館）'!E20+'SFF②（パピヨン24ガスホール）'!E20+'SFF③（大阪国際交流センター）'!E20+'SFF④（青葉の森公園芸術文化ホール） '!E20+'SFF⑤（松田町生涯学習センター） '!E20+'SFF⑥（ALL草加市文化会館）'!E20 -> 300000 | D20: ='SFF①（日野市民会館）'!F20+'SFF②（パピヨン24ガスホール）'!F20+'SFF③（大阪国際交流センター）'!F20+'SFF④（青葉の森公園芸術文化ホール） '!F20+'SFF⑤（松田町生涯学習センター） '!F20+'SFF⑥（ALL草加市文化会館）'!F20 -> 300000
A21: 人件費（MC） | B21: ='SFF①（日野市民会館）'!D21+'SFF②（パピヨン24ガスホール）'!D21+'SFF③（大阪国際交流センター）'!D21+'SFF④（青葉の森公園芸術文化ホール） '!D21+'SFF⑤（松田町生涯学習センター） '!D21+'SFF⑥（ALL草加市文化会館）'!D21 -> 0 | C21: ='SFF①（日野市民会館）'!E21+'SFF②（パピヨン24ガスホール）'!E21+'SFF③（大阪国際交流センター）'!E21+'SFF④（青葉の森公園芸術文化ホール） '!E21+'SFF⑤（松田町生涯学習センター） '!E21+'SFF⑥（ALL草加市文化会館）'!E21 -> 296000 | D21: ='SFF①（日野市民会館）'!F21+'SFF②（パピヨン24ガスホール）'!F21+'SFF③（大阪国際交流センター）'!F21+'SFF④（青葉の森公園芸術文化ホール） '!F21+'SFF⑤（松田町生涯学習センター） '!F21+'SFF⑥（ALL草加市文化会館）'!F21 -> 0
A22: 人件費（カメラ） | B22: ='SFF①（日野市民会館）'!D22+'SFF②（パピヨン24ガスホール）'!D22+'SFF③（大阪国際交流センター）'!D22+'SFF④（青葉の森公園芸術文化ホール） '!D22+'SFF⑤（松田町生涯学習センター） '!D22+'SFF⑥（ALL草加市文化会館）'!D22 -> 2350000 | C22: ='SFF①（日野市民会館）'!E22+'SFF②（パピヨン24ガスホール）'!E22+'SFF③（大阪国際交流センター）'!E22+'SFF④（青葉の森公園芸術文化ホール） '!E22+'SFF⑤（松田町生涯学習センター） '!E22+'SFF⑥（ALL草加市文化会館）'!E22 -> 2350000 | D22: ='SFF①（日野市民会館）'!F22+'SFF②（パピヨン24ガスホール）'!F22+'SFF③（大阪国際交流センター）'!F22+'SFF④（青葉の森公園芸術文化ホール） '!F22+'SFF⑤（松田町生涯学習センター） '!F22+'SFF⑥（ALL草加市文化会館）'!F22 -> 2350000 | E22: ='購入品リスト'!E11+'購入品リスト'!E13 -> 690162
A23: 人件費（運営スタッフ） | B23: ='SFF①（日野市民会館）'!D23+'SFF②（パピヨン24ガスホール）'!D23+'SFF③（大阪国際交流センター）'!D23+'SFF④（青葉の森公園芸術文化ホール） '!D23+'SFF⑤（松田町生涯学習センター） '!D23+'SFF⑥（ALL草加市文化会館）'!D23 -> 2300000 | C23: ='SFF①（日野市民会館）'!E23+'SFF②（パピヨン24ガスホール）'!E23+'SFF③（大阪国際交流センター）'!E23+'SFF④（青葉の森公園芸術文化ホール） '!E23+'SFF⑤（松田町生涯学習センター） '!E23+'SFF⑥（ALL草加市文化会館）'!E23 -> 2300000 | D23: ='SFF①（日野市民会館）'!F23+'SFF②（パピヨン24ガスホール）'!F23+'SFF③（大阪国際交流センター）'!F23+'SFF④（青葉の森公園芸術文化ホール） '!F23+'SFF⑤（松田町生涯学習センター） '!F23+'SFF⑥（ALL草加市文化会館）'!F23 -> 2300000
A24: メダルトロフィー代 | B24: ='SFF①（日野市民会館）'!D24+'SFF②（パピヨン24ガスホール）'!D24+'SFF③（大阪国際交流センター）'!D24+'SFF④（青葉の森公園芸術文化ホール） '!D24+'SFF⑤（松田町生涯学習センター） '!D24+'SFF⑥（ALL草加市文化会館）'!D24 -> 1200000 | C24: ='SFF①（日野市民会館）'!E24+'SFF②（パピヨン24ガスホール）'!E24+'SFF③（大阪国際交流センター）'!E24+'SFF④（青葉の森公園芸術文化ホール） '!E24+'SFF⑤（松田町生涯学習センター） '!E24+'SFF⑥（ALL草加市文化会館）'!E24 -> 1200000 | D24: ='SFF①（日野市民会館）'!F24+'SFF②（パピヨン24ガスホール）'!F24+'SFF③（大阪国際交流センター）'!F24+'SFF④（青葉の森公園芸術文化ホール） '!F24+'SFF⑤（松田町生涯学習センター） '!F24+'SFF⑥（ALL草加市文化会館）'!F24 -> 1200000 | E24: ='購入品リスト'!E4+'購入品リスト'!E5+'購入品リスト'!E6+'購入品リスト'!E7+'購入品リスト'!E10+'購入品リスト'!E12 -> 643745
A25: 会場費 | B25: ='SFF①（日野市民会館）'!D25+'SFF②（パピヨン24ガスホール）'!D25+'SFF③（大阪国際交流センター）'!D25+'SFF④（青葉の森公園芸術文化ホール） '!D25+'SFF⑤（松田町生涯学習センター） '!D25+'SFF⑥（ALL草加市文化会館）'!D25 -> 5800000 | C25: ='SFF①（日野市民会館）'!E25+'SFF②（パピヨン24ガスホール）'!E25+'SFF③（大阪国際交流センター）'!E25+'SFF④（青葉の森公園芸術文化ホール） '!E25+'SFF⑤（松田町生涯学習センター） '!E25+'SFF⑥（ALL草加市文化会館）'!E25 -> 5800000 | D25: ='SFF①（日野市民会館）'!F25+'SFF②（パピヨン24ガスホール）'!F25+'SFF③（大阪国際交流センター）'!F25+'SFF④（青葉の森公園芸術文化ホール） '!F25+'SFF⑤（松田町生涯学習センター） '!F25+'SFF⑥（ALL草加市文化会館）'!F25 -> 5800000
A26: 備品消耗品費 | B26: ='SFF①（日野市民会館）'!D26+'SFF②（パピヨン24ガスホール）'!D26+'SFF③（大阪国際交流センター）'!D26+'SFF④（青葉の森公園芸術文化ホール） '!D26+'SFF⑤（松田町生涯学習センター） '!D26+'SFF⑥（ALL草加市文化会館）'!D26 -> 390000 | C26: ='SFF①（日野市民会館）'!E26+'SFF②（パピヨン24ガスホール）'!E26+'SFF③（大阪国際交流センター）'!E26+'SFF④（青葉の森公園芸術文化ホール） '!E26+'SFF⑤（松田町生涯学習センター） '!E26+'SFF⑥（ALL草加市文化会館）'!E26 -> 390000 | D26: ='SFF①（日野市民会館）'!F26+'SFF②（パピヨン24ガスホール）'!F26+'SFF③（大阪国際交流センター）'!F26+'SFF④（青葉の森公園芸術文化ホール） '!F26+'SFF⑤（松田町生涯学習センター） '!F26+'SFF⑥（ALL草加市文化会館）'!F26 -> 390000
A27: 運搬費 | B27: ='SFF①（日野市民会館）'!D27+'SFF②（パピヨン24ガスホール）'!D27+'SFF③（大阪国際交流センター）'!D27+'SFF④（青葉の森公園芸術文化ホール） '!D27+'SFF⑤（松田町生涯学習センター） '!D27+'SFF⑥（ALL草加市文化会館）'!D27 -> 350000 | C27: ='SFF①（日野市民会館）'!E27+'SFF②（パピヨン24ガスホール）'!E27+'SFF③（大阪国際交流センター）'!E27+'SFF④（青葉の森公園芸術文化ホール） '!E27+'SFF⑤（松田町生涯学習センター） '!E27+'SFF⑥（ALL草加市文化会館）'!E27 -> 350000 | D27: ='SFF①（日野市民会館）'!F27+'SFF②（パピヨン24ガスホール）'!F27+'SFF③（大阪国際交流センター）'!F27+'SFF④（青葉の森公園芸術文化ホール） '!F27+'SFF⑤（松田町生涯学習センター） '!F27+'SFF⑥（ALL草加市文化会館）'!F27 -> 350000
A28: 旅費交通費 | B28: ='SFF①（日野市民会館）'!D28+'SFF②（パピヨン24ガスホール）'!D28+'SFF③（大阪国際交流センター）'!D28+'SFF④（青葉の森公園芸術文化ホール） '!D28+'SFF⑤（松田町生涯学習センター） '!D28+'SFF⑥（ALL草加市文化会館）'!D28 -> 428000 | C28: ='SFF①（日野市民会館）'!E28+'SFF②（パピヨン24ガスホール）'!E28+'SFF③（大阪国際交流センター）'!E28+'SFF④（青葉の森公園芸術文化ホール） '!E28+'SFF⑤（松田町生涯学習センター） '!E28+'SFF⑥（ALL草加市文化会館）'!E28 -> 428000 | D28: ='SFF①（日野市民会館）'!F28+'SFF②（パピヨン24ガスホール）'!F28+'SFF③（大阪国際交流センター）'!F28+'SFF④（青葉の森公園芸術文化ホール） '!F28+'SFF⑤（松田町生涯学習センター） '!F28+'SFF⑥（ALL草加市文化会館）'!F28 -> 428000 | E28: 高速代は計算に入れていない、新幹線や飛行機代の分。
A29: 打ち上げ代 | B29: ='SFF①（日野市民会館）'!D29+'SFF②（パピヨン24ガスホール）'!D29+'SFF③（大阪国際交流センター）'!D29+'SFF④（青葉の森公園芸術文化ホール） '!D29+'SFF⑤（松田町生涯学習センター） '!D29+'SFF⑥（ALL草加市文化会館）'!D29 -> 180000 | C29: ='SFF①（日野市民会館）'!E29+'SFF②（パピヨン24ガスホール）'!E29+'SFF③（大阪国際交流センター）'!E29+'SFF④（青葉の森公園芸術文化ホール） '!E29+'SFF⑤（松田町生涯学習センター） '!E29+'SFF⑥（ALL草加市文化会館）'!E29 -> 180000 | D29: ='SFF①（日野市民会館）'!F29+'SFF②（パピヨン24ガスホール）'!F29+'SFF③（大阪国際交流センター）'!F29+'SFF④（青葉の森公園芸術文化ホール） '!F29+'SFF⑤（松田町生涯学習センター） '!F29+'SFF⑥（ALL草加市文化会館）'!F29 -> 180000
A30: 通信費 | B30: ='SFF①（日野市民会館）'!D30+'SFF②（パピヨン24ガスホール）'!D30+'SFF③（大阪国際交流センター）'!D30+'SFF④（青葉の森公園芸術文化ホール） '!D30+'SFF⑤（松田町生涯学習センター） '!D30+'SFF⑥（ALL草加市文化会館）'!D30 -> 300000 | C30: ='SFF①（日野市民会館）'!E30+'SFF②（パピヨン24ガスホール）'!E30+'SFF③（大阪国際交流センター）'!E30+'SFF④（青葉の森公園芸術文化ホール） '!E30+'SFF⑤（松田町生涯学習センター） '!E30+'SFF⑥（ALL草加市文化会館）'!E30 -> 300000 | D30: ='SFF①（日野市民会館）'!F30+'SFF②（パピヨン24ガスホール）'!F30+'SFF③（大阪国際交流センター）'!F30+'SFF④（青葉の森公園芸術文化ホール） '!F30+'SFF⑤（松田町生涯学習センター） '!F30+'SFF⑥（ALL草加市文化会館）'!F30 -> 300000
A31: スタッフTシャツ代 | B31: ='SFF①（日野市民会館）'!D31+'SFF②（パピヨン24ガスホール）'!D31+'SFF③（大阪国際交流センター）'!D31+'SFF④（青葉の森公園芸術文化ホール） '!D31+'SFF⑤（松田町生涯学習センター） '!D31+'SFF⑥（ALL草加市文化会館）'!D31 -> 0 | C31: ='SFF①（日野市民会館）'!E31+'SFF②（パピヨン24ガスホール）'!E31+'SFF③（大阪国際交流センター）'!E31+'SFF④（青葉の森公園芸術文化ホール） '!E31+'SFF⑤（松田町生涯学習センター） '!E31+'SFF⑥（ALL草加市文化会館）'!E31 -> 0 | D31: ='SFF①（日野市民会館）'!F31+'SFF②（パピヨン24ガスホール）'!F31+'SFF③（大阪国際交流センター）'!F31+'SFF④（青葉の森公園芸術文化ホール） '!F31+'SFF⑤（松田町生涯学習センター） '!F31+'SFF⑥（ALL草加市文化会館）'!F31 -> 0
A32: 経費合計 | B32: =SUM(B13:B31) -> 23822319 | C32: =SUM(C13:C31) -> 24347073 | D32: =SUM(D13:D31) -> 24279828
A33: 利益合計 | B33: =B11-B32 -> 14004865 | C33: =C11-C32 -> 20894407 | D33: =D11-D32 -> 32105948
A34: 利益率 | B34: =B33/B11 -> 0.37023283 | C34: =C33/C11 -> 0.4618418 | D34: =D33/D11 -> 0.569398

Sheet SFF（全体結果）
A1: 項目
A2: 売上 | B2: 売上80％ | C2: 前年度参考予想 | D2: 売上120％
A3: 出場費 | B3: ='SFF①（日野市民会館）'!D3+'SFF②（パピヨン24ガスホール）'!D3+'SFF③（大阪国際交流センター）'!D3+'SFF④（青葉の森公園芸術文化ホール） '!D3+'SFF⑤（松田町生涯学習センター） '!D3+'SFF⑥（ALL草加市文化会館）'!D3 -> 4240000 | C3: ='SFF①（日野市民会館）'!E3+'SFF②（パピヨン24ガスホール）'!E3+'SFF③（大阪国際交流センター）'!E3+'SFF④（青葉の森公園芸術文化ホール） '!E3+'SFF⑤（松田町生涯学習センター） '!E3+'SFF⑥（ALL草加市文化会館）'!E3 -> 5300000 | D3: ='SFF①（日野市民会館）'!F3+'SFF②（パピヨン24ガスホール）'!F3+'SFF③（大阪国際交流センター）'!F3+'SFF④（青葉の森公園芸術文化ホール） '!F3+'SFF⑤（松田町生涯学習センター） '!F3+'SFF⑥（ALL草加市文化会館）'!F3 -> 6360000
A4: 客席代 | B4: ='SFF①（日野市民会館）'!D4+'SFF②（パピヨン24ガスホール）'!D4+'SFF③（大阪国際交流センター）'!D4+'SFF④（青葉の森公園芸術文化ホール） '!D4+'SFF⑤（松田町生涯学習センター） '!D4+'SFF⑥（ALL草加市文化会館）'!D4 -> 19295584 | C4: ='SFF①（日野市民会館）'!E4+'SFF②（パピヨン24ガスホール）'!E4+'SFF③（大阪国際交流センター）'!E4+'SFF④（青葉の森公園芸術文化ホール） '!E4+'SFF⑤（松田町生涯学習センター） '!E4+'SFF⑥（ALL草加市文化会館）'!E4 -> 24119480 | D4: ='SFF①（日野市民会館）'!F4+'SFF②（パピヨン24ガスホール）'!F4+'SFF③（大阪国際交流センター）'!F4+'SFF④（青葉の森公園芸術文化ホール） '!F4+'SFF⑤（松田町生涯学習センター） '!F4+'SFF⑥（ALL草加市文化会館）'!F4 -> 28943376
A5: バックサポート代 | B5: ='SFF①（日野市民会館）'!D5+'SFF②（パピヨン24ガスホール）'!D5+'SFF③（大阪国際交流センター）'!D5+'SFF④（青葉の森公園芸術文化ホール） '!D5+'SFF⑤（松田町生涯学習センター） '!D5+'SFF⑥（ALL草加市文化会館）'!D5 -> 1161600 | C5: ='SFF①（日野市民会館）'!E5+'SFF②（パピヨン24ガスホール）'!E5+'SFF③（大阪国際交流センター）'!E5+'SFF④（青葉の森公園芸術文化ホール） '!E5+'SFF⑤（松田町生涯学習センター） '!E5+'SFF⑥（ALL草加市文化会館）'!E5 -> 1452000 | D5: ='SFF①（日野市民会館）'!F5+'SFF②（パピヨン24ガスホール）'!F5+'SFF③（大阪国際交流センター）'!F5+'SFF④（青葉の森公園芸術文化ホール） '!F5+'SFF⑤（松田町生涯学習センター） '!F5+'SFF⑥（ALL草加市文化会館）'!F5 -> 1742400
A6: カラーリング代 | B6: ='SFF①（日野市民会館）'!D6+'SFF②（パピヨン24ガスホール）'!D6+'SFF③（大阪国際交流センター）'!D6+'SFF④（青葉の森公園芸術文化ホール） '!D6+'SFF⑤（松田町生涯学習センター） '!D6+'SFF⑥（ALL草加市文化会館）'!D6 -> 1056000 | C6: ='SFF①（日野市民会館）'!E6+'SFF②（パピヨン24ガスホール）'!E6+'SFF③（大阪国際交流センター）'!E6+'SFF④（青葉の森公園芸術文化ホール） '!E6+'SFF⑤（松田町生涯学習センター） '!E6+'SFF⑥（ALL草加市文化会館）'!E6 -> 1320000 | D6: ='SFF①（日野市民会館）'!F6+'SFF②（パピヨン24ガスホール）'!F6+'SFF③（大阪国際交流センター）'!F6+'SFF④（青葉の森公園芸術文化ホール） '!F6+'SFF⑤（松田町生涯学習センター） '!F6+'SFF⑥（ALL草加市文化会館）'!F6 -> 1584000
A7: アパレル売上 | B7: ='SFF①（日野市民会館）'!D7+'SFF②（パピヨン24ガスホール）'!D7+'SFF③（大阪国際交流センター）'!D7+'SFF④（青葉の森公園芸術文化ホール） '!D7+'SFF⑤（松田町生涯学習センター） '!D7+'SFF⑥（ALL草加市文化会館）'!D7 -> 928000 | C7: ='SFF①（日野市民会館）'!E7+'SFF②（パピヨン24ガスホール）'!E7+'SFF③（大阪国際交流センター）'!E7+'SFF④（青葉の森公園芸術文化ホール） '!E7+'SFF⑤（松田町生涯学習センター） '!E7+'SFF⑥（ALL草加市文化会館）'!E7 -> 1160000 | D7: ='SFF①（日野市民会館）'!F7+'SFF②（パピヨン24ガスホール）'!F7+'SFF③（大阪国際交流センター）'!F7+'SFF④（青葉の森公園芸術文化ホール） '!F7+'SFF⑤（松田町生涯学習センター） '!F7+'SFF⑥（ALL草加市文化会館）'!F7 -> 1392000
A8: 写真売上 | B8: ='SFF①（日野市民会館）'!D8+'SFF②（パピヨン24ガスホール）'!D8+'SFF③（大阪国際交流センター）'!D8+'SFF④（青葉の森公園芸術文化ホール） '!D8+'SFF⑤（松田町生涯学習センター） '!D8+'SFF⑥（ALL草加市文化会館）'!D8 -> 2256000 | C8: ='SFF①（日野市民会館）'!E8+'SFF②（パピヨン24ガスホール）'!E8+'SFF③（大阪国際交流センター）'!E8+'SFF④（青葉の森公園芸術文化ホール） '!E8+'SFF⑤（松田町生涯学習センター） '!E8+'SFF⑥（ALL草加市文化会館）'!E8 -> 2820000 | D8: ='SFF①（日野市民会館）'!F8+'SFF②（パピヨン24ガスホール）'!F8+'SFF③（大阪国際交流センター）'!F8+'SFF④（青葉の森公園芸術文化ホール） '!F8+'SFF⑤（松田町生涯学習センター） '!F8+'SFF⑥（ALL草加市文化会館）'!F8 -> 3384000
A9: 動画販売 | B9: ='SFF①（日野市民会館）'!D9+'SFF②（パピヨン24ガスホール）'!D9+'SFF③（大阪国際交流センター）'!D9+'SFF④（青葉の森公園芸術文化ホール） '!D9+'SFF⑤（松田町生涯学習センター） '!D9+'SFF⑥（ALL草加市文化会館）'!D9 -> 720000 | C9: ='SFF①（日野市民会館）'!E9+'SFF②（パピヨン24ガスホール）'!E9+'SFF③（大阪国際交流センター）'!E9+'SFF④（青葉の森公園芸術文化ホール） '!E9+'SFF⑤（松田町生涯学習センター） '!E9+'SFF⑥（ALL草加市文化会館）'!E9 -> 900000 | D9: ='SFF①（日野市民会館）'!F9+'SFF②（パピヨン24ガスホール）'!F9+'SFF③（大阪国際交流センター）'!F9+'SFF④（青葉の森公園芸術文化ホール） '!F9+'SFF⑤（松田町生涯学習センター） '!F9+'SFF⑥（ALL草加市文化会館）'!F9 -> 1080000
A10: 協賛金 | B10: ='SFF①（日野市民会館）'!D10+'SFF②（パピヨン24ガスホール）'!D10+'SFF③（大阪国際交流センター）'!D10+'SFF④（青葉の森公園芸術文化ホール） '!D10+'SFF⑤（松田町生涯学習センター） '!D10+'SFF⑥（ALL草加市文化会館）'!D10 -> 8170000 | C10: ='SFF①（日野市民会館）'!E10+'SFF②（パピヨン24ガスホール）'!E10+'SFF③（大阪国際交流センター）'!E10+'SFF④（青葉の森公園芸術文化ホール） '!E10+'SFF⑤（松田町生涯学習センター） '!E10+'SFF⑥（ALL草加市文化会館）'!E10 -> 8170000 | D10: ='SFF①（日野市民会館）'!F10+'SFF②（パピヨン24ガスホール）'!F10+'SFF③（大阪国際交流センター）'!F10+'SFF④（青葉の森公園芸術文化ホール） '!F10+'SFF⑤（松田町生涯学習センター） '!F10+'SFF⑥（ALL草加市文化会館）'!F10 -> 11900000
A11: 売上合計 | B11: =SUM(B3:B10) -> 37827184 | C11: =SUM(C3:C10) -> 45241480 | D11: =SUM(D3:D10) -> 56385776
A12: 経費
A13: 出場チケット手数料（3.6%) | B13: ='SFF①（日野市民会館）'!D13+'SFF②（パピヨン24ガスホール）'!D13+'SFF③（大阪国際交流センター）'!D13+'SFF④（青葉の森公園芸術文化ホール） '!D13+'SFF⑤（松田町生涯学習センター） '!D13+'SFF⑥（ALL草加市文化会館）'!D13 -> 152640 | C13: ='SFF①（日野市民会館）'!E13+'SFF②（パピヨン24ガスホール）'!E13+'SFF③（大阪国際交流センター）'!E13+'SFF④（青葉の森公園芸術文化ホール） '!E13+'SFF⑤（松田町生涯学習センター） '!E13+'SFF⑥（ALL草加市文化会館）'!E13 -> 190800 | D13: ='SFF①（日野市民会館）'!F13+'SFF②（パピヨン24ガスホール）'!F13+'SFF③（大阪国際交流センター）'!F13+'SFF④（青葉の森公園芸術文化ホール） '!F13+'SFF⑤（松田町生涯学習センター） '!F13+'SFF⑥（ALL草加市文化会館）'!F13 -> 228960
A14: 客席チケット手数料（3.6%) | B14: ='SFF①（日野市民会館）'!D14+'SFF②（パピヨン24ガスホール）'!D14+'SFF③（大阪国際交流センター）'!D14+'SFF④（青葉の森公園芸術文化ホール） '!D14+'SFF⑤（松田町生涯学習センター） '!D14+'SFF⑥（ALL草加市文化会館）'!D14 -> 694641.02 | C14: ='SFF①（日野市民会館）'!E14+'SFF②（パピヨン24ガスホール）'!E14+'SFF③（大阪国際交流センター）'!E14+'SFF④（青葉の森公園芸術文化ホール） '!E14+'SFF⑤（松田町生涯学習センター） '!E14+'SFF⑥（ALL草加市文化会館）'!E14 -> 868301.28 | D14: ='SFF①（日野市民会館）'!F14+'SFF②（パピヨン24ガスホール）'!F14+'SFF③（大阪国際交流センター）'!F14+'SFF④（青葉の森公園芸術文化ホール） '!F14+'SFF⑤（松田町生涯学習センター） '!F14+'SFF⑥（ALL草加市文化会館）'!F14 -> 1041961.5
A15: バックサポートチケット手数料（3.6%) | B15: ='SFF①（日野市民会館）'!D15+'SFF②（パピヨン24ガスホール）'!D15+'SFF③（大阪国際交流センター）'!D15+'SFF④（青葉の森公園芸術文化ホール） '!D15+'SFF⑤（松田町生涯学習センター） '!D15+'SFF⑥（ALL草加市文化会館）'!D15 -> 41817.6 | C15: ='SFF①（日野市民会館）'!E15+'SFF②（パピヨン24ガスホール）'!E15+'SFF③（大阪国際交流センター）'!E15+'SFF④（青葉の森公園芸術文化ホール） '!E15+'SFF⑤（松田町生涯学習センター） '!E15+'SFF⑥（ALL草加市文化会館）'!E15 -> 52272 | D15: ='SFF①（日野市民会館）'!F15+'SFF②（パピヨン24ガスホール）'!F15+'SFF③（大阪国際交流センター）'!F15+'SFF④（青葉の森公園芸術文化ホール） '!F15+'SFF⑤（松田町生涯学習センター） '!F15+'SFF⑥（ALL草加市文化会館）'!F15 -> 62726.4
A16: カラーリングチケット手数料（3.2%） | B16: ='SFF①（日野市民会館）'!D16+'SFF②（パピヨン24ガスホール）'!D16+'SFF③（大阪国際交流センター）'!D16+'SFF④（青葉の森公園芸術文化ホール） '!D16+'SFF⑤（松田町生涯学習センター） '!D16+'SFF⑥（ALL草加市文化会館）'!D16 -> 0 | C16: ='SFF①（日野市民会館）'!E16+'SFF②（パピヨン24ガスホール）'!E16+'SFF③（大阪国際交流センター）'!E16+'SFF④（青葉の森公園芸術文化ホール） '!E16+'SFF⑤（松田町生涯学習センター） '!E16+'SFF⑥（ALL草加市文化会館）'!E16 -> 0 | D16: ='SFF①（日野市民会館）'!F16+'SFF②（パピヨン24ガスホール）'!F16+'SFF③（大阪国際交流センター）'!F16+'SFF④（青葉の森公園芸術文化ホール） '!F16+'SFF⑤（松田町生涯学習センター） '!F16+'SFF⑥（ALL草加市文化会館）'!F16 -> 0
A17: 動画手数料（3.6%） | B17: ='SFF①（日野市民会館）'!D17+'SFF②（パピヨン24ガスホール）'!D17+'SFF③（大阪国際交流センター）'!D17+'SFF④（青葉の森公園芸術文化ホール） '!D17+'SFF⑤（松田町生涯学習センター） '!D17+'SFF⑥（ALL草加市文化会館）'!D17 -> 25920 | C17: ='SFF①（日野市民会館）'!E17+'SFF②（パピヨン24ガスホール）'!E17+'SFF③（大阪国際交流センター）'!E17+'SFF④（青葉の森公園芸術文化ホール） '!E17+'SFF⑤（松田町生涯学習センター） '!E17+'SFF⑥（ALL草加市文化会館）'!E17 -> 32400 | D17: ='SFF①（日野市民会館）'!F17+'SFF②（パピヨン24ガスホール）'!F17+'SFF③（大阪国際交流センター）'!F17+'SFF④（青葉の森公園芸術文化ホール） '!F17+'SFF⑤（松田町生涯学習センター） '!F17+'SFF⑥（ALL草加市文化会館）'!F17 -> 38880
A18: アパレル仕入れ | B18: ='SFF①（日野市民会館）'!D18+'SFF②（パピヨン24ガスホール）'!D18+'SFF③（大阪国際交流センター）'!D18+'SFF④（青葉の森公園芸術文化ホール） '!D18+'SFF⑤（松田町生涯学習センター） '!D18+'SFF⑥（ALL草加市文化会館）'!D18 -> 1400000 | C18: ='SFF①（日野市民会館）'!E18+'SFF②（パピヨン24ガスホール）'!E18+'SFF③（大阪国際交流センター）'!E18+'SFF④（青葉の森公園芸術文化ホール） '!E18+'SFF⑤（松田町生涯学習センター） '!E18+'SFF⑥（ALL草加市文化会館）'!E18 -> 1400000 | D18: ='SFF①（日野市民会館）'!F18+'SFF②（パピヨン24ガスホール）'!F18+'SFF③（大阪国際交流センター）'!F18+'SFF④（青葉の森公園芸術文化ホール） '!F18+'SFF⑤（松田町生涯学習センター） '!F18+'SFF⑥（ALL草加市文化会館）'!F18 -> 1400000
A19: 演出費 | B19: ='SFF①（日野市民会館）'!D19+'SFF②（パピヨン24ガスホール）'!D19+'SFF③（大阪国際交流センター）'!D19+'SFF④（青葉の森公園芸術文化ホール） '!D19+'SFF⑤（松田町生涯学習センター） '!D19+'SFF⑥（ALL草加市文化会館）'!D19 -> 7909300 | C19: ='SFF①（日野市民会館）'!E19+'SFF②（パピヨン24ガスホール）'!E19+'SFF③（大阪国際交流センター）'!E19+'SFF④（青葉の森公園芸術文化ホール） '!E19+'SFF⑤（松田町生涯学習センター） '!E19+'SFF⑥（ALL草加市文化会館）'!E19 -> 7909300 | D19: ='SFF①（日野市民会館）'!F19+'SFF②（パピヨン24ガスホール）'!F19+'SFF③（大阪国際交流センター）'!F19+'SFF④（青葉の森公園芸術文化ホール） '!F19+'SFF⑤（松田町生涯学習センター） '!F19+'SFF⑥（ALL草加市文化会館）'!F19 -> 7909300
A20: 人件費（審査員） | B20: ='SFF①（日野市民会館）'!D20+'SFF②（パピヨン24ガスホール）'!D20+'SFF③（大阪国際交流センター）'!D20+'SFF④（青葉の森公園芸術文化ホール） '!D20+'SFF⑤（松田町生涯学習センター） '!D20+'SFF⑥（ALL草加市文化会館）'!D20 -> 300000 | C20: ='SFF①（日野市民会館）'!E20+'SFF②（パピヨン24ガスホール）'!E20+'SFF③（大阪国際交流センター）'!E20+'SFF④（青葉の森公園芸術文化ホール） '!E20+'SFF⑤（松田町生涯学習センター） '!E20+'SFF⑥（ALL草加市文化会館）'!E20 -> 300000 | D20: ='SFF①（日野市民会館）'!F20+'SFF②（パピヨン24ガスホール）'!F20+'SFF③（大阪国際交流センター）'!F20+'SFF④（青葉の森公園芸術文化ホール） '!F20+'SFF⑤（松田町生涯学習センター） '!F20+'SFF⑥（ALL草加市文化会館）'!F20 -> 300000
A21: 人件費（MC） | B21: ='SFF①（日野市民会館）'!D21+'SFF②（パピヨン24ガスホール）'!D21+'SFF③（大阪国際交流センター）'!D21+'SFF④（青葉の森公園芸術文化ホール） '!D21+'SFF⑤（松田町生涯学習センター） '!D21+'SFF⑥（ALL草加市文化会館）'!D21 -> 0 | C21: ='SFF①（日野市民会館）'!E21+'SFF②（パピヨン24ガスホール）'!E21+'SFF③（大阪国際交流センター）'!E21+'SFF④（青葉の森公園芸術文化ホール） '!E21+'SFF⑤（松田町生涯学習センター） '!E21+'SFF⑥（ALL草加市文化会館）'!E21 -> 296000 | D21: ='SFF①（日野市民会館）'!F21+'SFF②（パピヨン24ガスホール）'!F21+'SFF③（大阪国際交流センター）'!F21+'SFF④（青葉の森公園芸術文化ホール） '!F21+'SFF⑤（松田町生涯学習センター） '!F21+'SFF⑥（ALL草加市文化会館）'!F21 -> 0
A22: 人件費（カメラ） | B22: ='SFF①（日野市民会館）'!D22+'SFF②（パピヨン24ガスホール）'!D22+'SFF③（大阪国際交流センター）'!D22+'SFF④（青葉の森公園芸術文化ホール） '!D22+'SFF⑤（松田町生涯学習センター） '!D22+'SFF⑥（ALL草加市文化会館）'!D22 -> 2350000 | C22: ='SFF①（日野市民会館）'!E22+'SFF②（パピヨン24ガスホール）'!E22+'SFF③（大阪国際交流センター）'!E22+'SFF④（青葉の森公園芸術文化ホール） '!E22+'SFF⑤（松田町生涯学習センター） '!E22+'SFF⑥（ALL草加市文化会館）'!E22 -> 2350000 | D22: ='SFF①（日野市民会館）'!F22+'SFF②（パピヨン24ガスホール）'!F22+'SFF③（大阪国際交流センター）'!F22+'SFF④（青葉の森公園芸術文化ホール） '!F22+'SFF⑤（松田町生涯学習センター） '!F22+'SFF⑥（ALL草加市文化会館）'!F22 -> 2350000 | E22: ='購入品リスト'!E11+'購入品リスト'!E13 -> 690162
A23: 人件費（運営スタッフ） | B23: ='SFF①（日野市民会館）'!D23+'SFF②（パピヨン24ガスホール）'!D23+'SFF③（大阪国際交流センター）'!D23+'SFF④（青葉の森公園芸術文化ホール） '!D23+'SFF⑤（松田町生涯学習センター） '!D23+'SFF⑥（ALL草加市文化会館）'!D23 -> 2300000 | C23: ='SFF①（日野市民会館）'!E23+'SFF②（パピヨン24ガスホール）'!E23+'SFF③（大阪国際交流センター）'!E23+'SFF④（青葉の森公園芸術文化ホール） '!E23+'SFF⑤（松田町生涯学習センター） '!E23+'SFF⑥（ALL草加市文化会館）'!E23 -> 2300000 | D23: ='SFF①（日野市民会館）'!F23+'SFF②（パピヨン24ガスホール）'!F23+'SFF③（大阪国際交流センター）'!F23+'SFF④（青葉の森公園芸術文化ホール） '!F23+'SFF⑤（松田町生涯学習センター） '!F23+'SFF⑥（ALL草加市文化会館）'!F23 -> 2300000
A24: メダルトロフィー代 | B24: ='SFF①（日野市民会館）'!D24+'SFF②（パピヨン24ガスホール）'!D24+'SFF③（大阪国際交流センター）'!D24+'SFF④（青葉の森公園芸術文化ホール） '!D24+'SFF⑤（松田町生涯学習センター） '!D24+'SFF⑥（ALL草加市文化会館）'!D24 -> 1200000 | C24: ='SFF①（日野市民会館）'!E24+'SFF②（パピヨン24ガスホール）'!E24+'SFF③（大阪国際交流センター）'!E24+'SFF④（青葉の森公園芸術文化ホール） '!E24+'SFF⑤（松田町生涯学習センター） '!E24+'SFF⑥（ALL草加市文化会館）'!E24 -> 1200000 | D24: ='SFF①（日野市民会館）'!F24+'SFF②（パピヨン24ガスホール）'!F24+'SFF③（大阪国際交流センター）'!F24+'SFF④（青葉の森公園芸術文化ホール） '!F24+'SFF⑤（松田町生涯学習センター） '!F24+'SFF⑥（ALL草加市文化会館）'!F24 -> 1200000 | E24: ='購入品リスト'!E4+'購入品リスト'!E5+'購入品リスト'!E6+'購入品リスト'!E7+'購入品リスト'!E10+'購入品リスト'!E12 -> 643745
A25: 会場費 | B25: ='SFF①（日野市民会館）'!D25+'SFF②（パピヨン24ガスホール）'!D25+'SFF③（大阪国際交流センター）'!D25+'SFF④（青葉の森公園芸術文化ホール） '!D25+'SFF⑤（松田町生涯学習センター） '!D25+'SFF⑥（ALL草加市文化会館）'!D25 -> 5800000 | C25: ='SFF①（日野市民会館）'!E25+'SFF②（パピヨン24ガスホール）'!E25+'SFF③（大阪国際交流センター）'!E25+'SFF④（青葉の森公園芸術文化ホール） '!E25+'SFF⑤（松田町生涯学習センター） '!E25+'SFF⑥（ALL草加市文化会館）'!E25 -> 5800000 | D25: ='SFF①（日野市民会館）'!F25+'SFF②（パピヨン24ガスホール）'!F25+'SFF③（大阪国際交流センター）'!F25+'SFF④（青葉の森公園芸術文化ホール） '!F25+'SFF⑤（松田町生涯学習センター） '!F25+'SFF⑥（ALL草加市文化会館）'!F25 -> 5800000
A26: 備品消耗品費 | B26: ='SFF①（日野市民会館）'!D26+'SFF②（パピヨン24ガスホール）'!D26+'SFF③（大阪国際交流センター）'!D26+'SFF④（青葉の森公園芸術文化ホール） '!D26+'SFF⑤（松田町生涯学習センター） '!D26+'SFF⑥（ALL草加市文化会館）'!D26 -> 390000 | C26: ='SFF①（日野市民会館）'!E26+'SFF②（パピヨン24ガスホール）'!E26+'SFF③（大阪国際交流センター）'!E26+'SFF④（青葉の森公園芸術文化ホール） '!E26+'SFF⑤（松田町生涯学習センター） '!E26+'SFF⑥（ALL草加市文化会館）'!E26 -> 390000 | D26: ='SFF①（日野市民会館）'!F26+'SFF②（パピヨン24ガスホール）'!F26+'SFF③（大阪国際交流センター）'!F26+'SFF④（青葉の森公園芸術文化ホール） '!F26+'SFF⑤（松田町生涯学習センター） '!F26+'SFF⑥（ALL草加市文化会館）'!F26 -> 390000
A27: 運搬費 | B27: ='SFF①（日野市民会館）'!D27+'SFF②（パピヨン24ガスホール）'!D27+'SFF③（大阪国際交流センター）'!D27+'SFF④（青葉の森公園芸術文化ホール） '!D27+'SFF⑤（松田町生涯学習センター） '!D27+'SFF⑥（ALL草加市文化会館）'!D27 -> 350000 | C27: ='SFF①（日野市民会館）'!E27+'SFF②（パピヨン24ガスホール）'!E27+'SFF③（大阪国際交流センター）'!E27+'SFF④（青葉の森公園芸術文化ホール） '!E27+'SFF⑤（松田町生涯学習センター） '!E27+'SFF⑥（ALL草加市文化会館）'!E27 -> 350000 | D27: ='SFF①（日野市民会館）'!F27+'SFF②（パピヨン24ガスホール）'!F27+'SFF③（大阪国際交流センター）'!F27+'SFF④（青葉の森公園芸術文化ホール） '!F27+'SFF⑤（松田町生涯学習センター） '!F27+'SFF⑥（ALL草加市文化会館）'!F27 -> 350000
A28: 旅費交通費 | B28: ='SFF①（日野市民会館）'!D28+'SFF②（パピヨン24ガスホール）'!D28+'SFF③（大阪国際交流センター）'!D28+'SFF④（青葉の森公園芸術文化ホール） '!D28+'SFF⑤（松田町生涯学習センター） '!D28+'SFF⑥（ALL草加市文化会館）'!D28 -> 428000 | C28: ='SFF①（日野市民会館）'!E28+'SFF②（パピヨン24ガスホール）'!E28+'SFF③（大阪国際交流センター）'!E28+'SFF④（青葉の森公園芸術文化ホール） '!E28+'SFF⑤（松田町生涯学習センター） '!E28+'SFF⑥（ALL草加市文化会館）'!E28 -> 428000 | D28: ='SFF①（日野市民会館）'!F28+'SFF②（パピヨン24ガスホール）'!F28+'SFF③（大阪国際交流センター）'!F28+'SFF④（青葉の森公園芸術文化ホール） '!F28+'SFF⑤（松田町生涯学習センター） '!F28+'SFF⑥（ALL草加市文化会館）'!F28 -> 428000 | E28: 高速代は計算に入れていない、新幹線や飛行機代の分。
A29: 打ち上げ代 | B29: ='SFF①（日野市民会館）'!D29+'SFF②（パピヨン24ガスホール）'!D29+'SFF③（大阪国際交流センター）'!D29+'SFF④（青葉の森公園芸術文化ホール） '!D29+'SFF⑤（松田町生涯学習センター） '!D29+'SFF⑥（ALL草加市文化会館）'!D29 -> 180000 | C29: ='SFF①（日野市民会館）'!E29+'SFF②（パピヨン24ガスホール）'!E29+'SFF③（大阪国際交流センター）'!E29+'SFF④（青葉の森公園芸術文化ホール） '!E29+'SFF⑤（松田町生涯学習センター） '!E29+'SFF⑥（ALL草加市文化会館）'!E29 -> 180000 | D29: ='SFF①（日野市民会館）'!F29+'SFF②（パピヨン24ガスホール）'!F29+'SFF③（大阪国際交流センター）'!F29+'SFF④（青葉の森公園芸術文化ホール） '!F29+'SFF⑤（松田町生涯学習センター） '!F29+'SFF⑥（ALL草加市文化会館）'!F29 -> 180000
A30: 通信費 | B30: ='SFF①（日野市民会館）'!D30+'SFF②（パピヨン24ガスホール）'!D30+'SFF③（大阪国際交流センター）'!D30+'SFF④（青葉の森公園芸術文化ホール） '!D30+'SFF⑤（松田町生涯学習センター） '!D30+'SFF⑥（ALL草加市文化会館）'!D30 -> 300000 | C30: ='SFF①（日野市民会館）'!E30+'SFF②（パピヨン24ガスホール）'!E30+'SFF③（大阪国際交流センター）'!E30+'SFF④（青葉の森公園芸術文化ホール） '!E30+'SFF⑤（松田町生涯学習センター） '!E30+'SFF⑥（ALL草加市文化会館）'!E30 -> 300000 | D30: ='SFF①（日野市民会館）'!F30+'SFF②（パピヨン24ガスホール）'!F30+'SFF③（大阪国際交流センター）'!F30+'SFF④（青葉の森公園芸術文化ホール） '!F30+'SFF⑤（松田町生涯学習センター） '!F30+'SFF⑥（ALL草加市文化会館）'!F30 -> 300000
A31: スタッフTシャツ代 | B31: ='SFF①（日野市民会館）'!D31+'SFF②（パピヨン24ガスホール）'!D31+'SFF③（大阪国際交流センター）'!D31+'SFF④（青葉の森公園芸術文化ホール） '!D31+'SFF⑤（松田町生涯学習センター） '!D31+'SFF⑥（ALL草加市文化会館）'!D31 -> 0 | C31: ='SFF①（日野市民会館）'!E31+'SFF②（パピヨン24ガスホール）'!E31+'SFF③（大阪国際交流センター）'!E31+'SFF④（青葉の森公園芸術文化ホール） '!E31+'SFF⑤（松田町生涯学習センター） '!E31+'SFF⑥（ALL草加市文化会館）'!E31 -> 0 | D31: ='SFF①（日野市民会館）'!F31+'SFF②（パピヨン24ガスホール）'!F31+'SFF③（大阪国際交流センター）'!F31+'SFF④（青葉の森公園芸術文化ホール） '!F31+'SFF⑤（松田町生涯学習センター） '!F31+'SFF⑥（ALL草加市文化会館）'!F31 -> 0
A32: 経費合計 | B32: =SUM(B13:B31) -> 23822319 | C32: =SUM(C13:C31) -> 24347073 | D32: =SUM(D13:D31) -> 24279828
A33: 利益合計 | B33: =B11-B32 -> 14004865 | C33: =C11-C32 -> 20894407 | D33: =D11-D32 -> 32105948
A34: 利益率 | B34: =B33/B11 -> 0.37023283 | C34: =C33/C11 -> 0.4618418 | D34: =D33/D11 -> 0.569398

Sheet SFF①（日野市民会館）
A1: 項目 | B1: 設定 | C1: 単価 | E1: 5/25 東京 日野市民会館
A2: 売上 | D2: 売上80％ | E2: 前年度参考予想 | F2: 売上120％ | G2: 実数値
A3: 出場費 | B3: 300人定員 200人と仮定 | C3: 5000 | D3: =E3*0.8 -> 800000 | E3: =200*C3 -> 1000000 | F3: =E3*1.2 -> 1200000 | G3: =C3*222 -> 1110000
A4: 客席代 | B4: 1,000席内訳：S142席、A581席、B338席の７割想定 価格：S7,000円、A6,000円、B5,000円 | C4: 5500 | D4: =E4*0.8 -> 3800720 | E4: =(7700*142*0.7+6600*581*0.7+5500*338*0.7) -> 4750900 | F4: =E4*1.2 -> 5701080 | G4: =(7700*142+6600*298+5500*272) -> 4556200
A5: バックサポート代 | B5: 出場者40％想定 | C5: 3300 | D5: =E5*0.8 -> 211200 | E5: =200*0.4*C5 -> 264000 | F5: =E5*1.2 -> 316800 | G5: 293700
A6: カラーリング代 | B6: 出場者40%人想定(23年度Tokyo大会参考) 25%フィー | C6: 11000 | D6: =E6*0.8 -> 176000 | E6: =200*0.4*C6*0.25 -> 220000 | F6: =E6*1.2 -> 264000 | G6: 250250
A7: アパレル売上 | B7: 23年度Tokyo大会参考 | D7: =E7*0.8 -> 160000 | E7: 200000 | F7: =E7*1.2 -> 240000 | G7: 384900
A8: 写真売上 | B8: 23年度Tokyo大会参考 | D8: =E8*0.8 -> 376000 | E8: 470000 | F8: =E8*1.2 -> 564000
A9: 動画販売 | D9: =E9*0.8 -> 120000 | E9: 150000 | F9: =E9*1.2 -> 180000 | G9: 224000
A10: 協賛金 | D10: 1200000 | E10: 1200000 | F10: 1950000 | G10: ='協賛金計算'!I11 -> 1525000
A11: 売上合計 | D11: =SUM(D3:D10) -> 6843920 | E11: =SUM(E3:E10) -> 8254900 | F11: =SUM(F3:F10) -> 10415880 | G11: =SUM(G3:G10) -> 8344050
A12: 経費
A13: 出場チケット手数料（3.6%) | D13: =D3*0.036 -> 28800 | E13: =E3*0.036 -> 36000 | F13: =F3*0.036 -> 43200 | G13: =G3*0.036 -> 39960
A14: 客席チケット手数料（3.6%) | D14: =D4*0.036 -> 136825.92 | E14: =E4*0.036 -> 171032.4 | F14: =F4*0.036 -> 205238.88 | G14: =G4*0.036 -> 164023.2
A15: バックサポートチケット手数料（3.6%) | D15: =D5*0.036 -> 7603.2 | E15: =E5*0.036 -> 9504 | F15: =F5*0.036 -> 11404.8 | G15: =G5*0.036 -> 10573.2
A16: カラーリングチケット手数料（3.2%） | B16: 出場者40％想定＊3.2% | C16: 5000 | E16: 0
A17: 動画手数料（3.6%） | D17: =D9*0.036 -> 4320 | E17: =E9*0.036 -> 5400 | F17: =F9*0.036 -> 6480
A18: アパレル仕入れ | B18: 23年度3大会アパレル仕入れを/3 | D18: 100000 | E18: 100000 | F18: 100000
A19: 演出費 | B19: 2/17見積（舞台監督費用含む）【東京】株式会社Shape Fit御中_ShapeFitFestival東京大会 日野市民会館_見積書_Q-0000000003.pdf | D19: 1120900 | E19: 1120900 | F19: 1120900
A20: 人件費（審査員） | B20: 5名 | C20: 10000 | D20: 50000 | E20: =C20*5 -> 50000 | F20: 50000 | G20: =15000*3+10000*2 -> 65000
A21: 人件費（MC） | B21: えいみーさん（5万円＋交通費） | E21: 55000 | G21: 50495
A22: 人件費（カメラ） | B22: 23年度1大会あたり | D22: =E22 -> 350000 | E22: 350000 | F22: =E22 -> 350000
A23: 人件費（運営スタッフ） | B23: 25人想定（東京大会最大30人弱のため） | C23: 9000 | D23: 225000 | E23: =C23*25 -> 225000 | F23: 225000
A24: メダルトロフィー代 | B24: 23年度3大会仕入れを/3 | D24: 200000 | E24: 200000 | F24: 200000
A25: 会場費 | B25: すでに301,510円支払(23年度参考) | D25: =E25 -> 650000 | E25: 650000 | F25: =E25 -> 650000
A26: 備品消耗品費 | B26: 23年度参考（トランシーバー20,000円、リストバンド等50,000円） | D26: 65000 | E26: 65000 | F26: 65000
A27: 運搬費 | B27: 荷物集荷（往復） | D27: 30000 | E27: 30000 | F27: 30000
A28: 旅費交通費 | B28: 下見等（往復2,000＊6人） | D28: 12000 | E28: 12000 | F28: 12000
A29: 打ち上げ代 | B29: 審査員ご飯、打ち上げあり | D29: 30000 | E29: 30000 | F29: 30000
A30: 通信費 | D30: 50000 | E30: 50000 | F30: 50000
A31: スタッフTシャツ代
A32: 経費合計 | D32: =SUM(D13:D31) -> 3060449.1 | E32: =SUM(E13:E31) -> 3159836.4 | F32: =SUM(F13:F31) -> 3149223.7
A33: 利益合計 | D33: =D11-D32 -> 3783470.9 | E33: =E11-E32 -> 5095063.6 | F33: =F11-F32 -> 7266656.3
A34: 利益率 | D34: =D33/D11 -> 0.5528222 | E34: =E33/E11 -> 0.61721688 | F34: =F33/F11 -> 0.69765169

Sheet SFF②（パピヨン24ガスホール）
A1: 項目 | B1: 設定 | C1: 単価 | E1: 6/14 福岡 パピヨン24ガスホール
A2: 売上 | D2: 売上80％ | E2: 前年度参考予想 | F2: 売上120％ | G2: 実数値
A3: 出場費 | B3: 200人キャパのため100人想定 | C3: 5000 | D3: =E3*0.8 -> 400000 | E3: =100*C3 -> 500000 | F3: =E3*1.2 -> 600000 | G3: =C3*123 -> 615000
A4: 客席代 | B4: 1,000席内訳：S91席、A132席、B188席の７割想定 価格：S7,000円、A6,000円、B5,000円 | C4: 5500 | D4: =E4*0.8 -> 1459304 | E4: =7700*91*0.7+6600*132*0.7+5500*188*0.7 -> 1824130 | F4: =E4*1.2 -> 2188956 | G4: =7700*91+6600*132+5500*183 -> 2578400 | H4: ※当日現金払い
A5: バックサポート代 | B5: 出場者40％想定 | C5: 3300 | D5: =E5*0.8 -> 211200 | E5: =200*0.4*C5 -> 264000 | F5: =E5*1.2 -> 316800 | G5: =C5*58 -> 191400
A6: カラーリング代 | B6: 出場者40%人想定(23年度Tokyo大会参考) 25%フィー | C6: 11000 | D6: =E6*0.8 -> 176000 | E6: =200*0.4*C6*0.25 -> 220000 | F6: =E6*1.2 -> 264000 | G6: 38206
A7: アパレル売上 | B7: 23年度Tokyo大会参考 | D7: =E7*0.8 -> 160000 | E7: 200000 | F7: =E7*1.2 -> 240000 | G7: 332200
A8: 写真売上 | B8: 23年度Tokyo大会参考 | D8: =E8*0.8 -> 376000 | E8: 470000 | F8: =E8*1.2 -> 564000 | G8: 280660
A9: 動画販売 | D9: =E9*0.8 -> 120000 | E9: 150000 | F9: =E9*1.2 -> 180000 | G9: 91000
A10: 協賛金 | D10: 500000 | E10: 500000 | F10: 900000 | G10: ='協賛金計算'!I12 -> 685000
A11: 売上合計 | D11: =SUM(D3:D10) -> 3402504 | E11: =SUM(E3:E10) -> 4128130 | F11: =SUM(F3:F10) -> 5253756 | G11: =SUM(G3:G10) -> 4811866
A12: 経費
A13: 出場チケット手数料（3.6%) | D13: =D3*0.036 -> 14400 | E13: =E3*0.036 -> 18000 | F13: =F3*0.036 -> 21600
A14: 客席チケット手数料（3.6%) | D14: =D4*0.036 -> 52534.944 | E14: =E4*0.036 -> 65668.68 | F14: =F4*0.036 -> 78802.416
A15: バックサポートチケット手数料（3.6%) | D15: =D5*0.036 -> 7603.2 | E15: =E5*0.036 -> 9504 | F15: =F5*0.036 -> 11404.8
A16: カラーリングチケット手数料（3.2%） | B16: 出場者40％想定＊3.2% | C16: 5000 | E16: 0
A17: 動画手数料（3.6%） | D17: =D9*0.036 -> 4320 | E17: =E9*0.036 -> 5400 | F17: =F9*0.036 -> 6480
A18: アパレル仕入れ | B18: 23年度3大会アパレル仕入れを/3 | D18: 100000 | E18: 100000 | F18: 100000
A19: 演出費 | B19: 2/17見積（舞台監督費用含む）＋宿泊費交通費別途のため見積もりプラスで見積もり【福岡】株式会社Shape Fit御中_ShapeFitFestival福岡大会 パピヨン24ガスホール_見積書_Q-0000000004.pdf | D19: 950000 | E19: 950000 | F19: 950000
A20: 人件費（審査員） | B20: 関東2名（40,000円）、関西1名（35,000円） | C20: 10000 | D20: 50000 | E20: =C20*5 -> 50000 | F20: 50000 | G20: =40000*2+35000 -> 115000
A21: 人件費（MC） | B21: ぷり（3万＋交通費） | E21: 60000 | G21: =30000+35000 -> 65000
A22: 人件費（カメラ） | B22: 23年度1大会あたり＋（交通費30,000円＊5人） | D22: =350000+150000 -> 500000 | E22: =350000+150000 -> 500000 | F22: =350000+150000 -> 500000
A23: 人件費（運営スタッフ） | B23: 20人想定（外部13人＋7人）交通費含む | C23: 40000 | D23: =E23 -> 800000 | E23: =C23*20 -> 800000 | F23: =E23 -> 800000
A24: メダルトロフィー、バッチ代 | B24: 23年度3大会仕入れを/3 | D24: 200000 | E24: 200000 | F24: 200000
A25: 会場費 | B25: すでに313,005円支払(23年度参考) | D25: =E25 -> 650000 | E25: 650000 | F25: =E25 -> 650000
A26: 備品消耗品費 | B26: 23年度参考（トランシーバー20,000円、リストバンド等50,000円） | D26: 65000 | E26: 65000 | F26: 65000
A27: 運搬費 | B27: 荷物集荷（往復）＊東京の1.5倍の | D27: =60000+140000 -> 200000 | E27: =60000+140000 -> 200000 | F27: =60000+140000 -> 200000
A28: 旅費交通費 | B28: 下見等（往復30,000人*2）＋宿泊費（23年大阪参考：140,000円） | D28: =E28 -> 200000 | E28: =60000+140000 -> 200000 | F28: =E28 -> 200000
A29: 打ち上げ代 | B29: 審査員ご飯、打ち上げあり | D29: 30000 | E29: 30000 | F29: =E29 -> 30000
A30: 通信費 | D30: 50000 | E30: 50000 | F30: 50000
A31: スタッフTシャツ代
A32: 経費合計 | D32: =SUM(D13:D31) -> 3873858.1 | E32: =SUM(E13:E31) -> 3953572.7 | F32: =SUM(F13:F31) -> 3913287.2
A33: 利益合計 | D33: =D11-D32 -> -471354.14 | E33: =E11-E32 -> 174557.32 | F33: =F11-F32 -> 1340468.8
A34: 利益率 | D34: =D33/D11 -> -0.13853155 | E34: =E33/E11 -> 0.042284841 | F34: =F33/F11 -> 0.25514485
A35: 宿泊費
A36: 移動費

Sheet SFF③（大阪国際交流センター）
A1: 項目 | B1: 設定 | C1: 単価 | E1: 7/27 大阪 大阪国際交流センター
A2: 売上 | D2: 売上80％ | E2: 前年度参考予想 | F2: 売上120％ | G2: 実数値
A3: 出場費 | B3: 180~220想定のため、200人と仮定 | C3: 5000 | D3: =E3*0.8 -> 800000 | E3: =200*C3 -> 1000000 | F3: =E3*1.2 -> 1200000 | G3: =C3*303 -> 1515000
A4: 客席代 | B4: 1,000席内訳：S154席、A260席、B560席の７割想定 価格：S7,000円、A6,000円、B5,000円 | C4: 5500 | D4: =E4*0.8 -> 3349808 | E4: =7700*154*0.7+6600*260*0.7+5500*560*0.7 -> 4187260 | F4: =E4*1.2 -> 5024712 | G4: =7700*154+6600*260+5500*560 -> 5981800
A5: バックサポート代 | B5: 出場者40％想定 | C5: 3300 | D5: =E5*0.8 -> 211200 | E5: =200*0.4*C5 -> 264000 | F5: =E5*1.2 -> 316800 | G5: =C5*172 -> 567600
A6: カラーリング代 | B6: 出場者40%人想定(23年度Tokyo大会参考) 25%フィー | C6: 11000 | D6: =E6*0.8 -> 176000 | E6: =200*0.4*C6*0.25 -> 220000 | F6: =E6*1.2 -> 264000 | G6: 134954
A7: アパレル売上 | B7: 23年度Tokyo大会参考 | D7: =E7*0.8 -> 160000 | E7: 200000 | F7: =E7*1.2 -> 240000 | G7: 447800
A8: 写真売上 | B8: 23年度Tokyo大会参考 | D8: =E8*0.8 -> 376000 | E8: 470000 | F8: =E8*1.2 -> 564000 | G8: 564220
A9: 動画販売 | D9: =E9*0.8 -> 120000 | E9: 150000 | F9: =E9*1.2 -> 180000
A10: 協賛金 | D10: 1000000 | E10: 1000000 | F10: 1600000 | G10: ='協賛金計算'!I13 -> 1250000
A11: 売上合計 | D11: =SUM(D3:D9) -> 5193008 | E11: =SUM(E3:E9) -> 6491260 | F11: =SUM(F3:F9) -> 7789512
A12: 経費
A13: 出場チケット手数料（3.6%) | D13: =D3*0.036 -> 28800 | E13: =E3*0.036 -> 36000 | F13: =F3*0.036 -> 43200
A14: 客席チケット手数料（3.6%) | D14: =D4*0.036 -> 120593.09 | E14: =E4*0.036 -> 150741.36 | F14: =F4*0.036 -> 180889.63
A15: バックサポートチケット手数料（3.6%) | D15: =D5*0.036 -> 7603.2 | E15: =E5*0.036 -> 9504 | F15: =F5*0.036 -> 11404.8
A16: カラーリングチケット手数料（3.2%） | B16: 出場者40％想定＊3.2% | C16: 5000 | E16: 0
A17: 動画手数料（3.6%） | D17: =D9*0.036 -> 4320 | E17: =E9*0.036 -> 5400 | F17: =F9*0.036 -> 6480
A18: アパレル仕入れ | B18: 23年度3大会アパレル仕入れを/3 | D18: 100000 | E18: 100000 | F18: 100000
A19: 演出費 | B19: 2/17見積（舞台監督費用含む）【大阪】株式会社Shape Fit御中_ShapeFitFestival大阪大会 大阪国際交流センター_見積書_Q-0000000005.pdf | D19: 950000 | E19: 950000 | F19: 950000
A20: 人件費（審査員） | B20: 5名 | C20: 10000 | D20: 50000 | E20: =C20*5 -> 50000 | F20: 50000 | G20: =15000*3+10000*2 -> 65000
A21: 人件費（MC） | B21: おのっち（3万＋交通費） | E21: 33000
A22: 人件費（カメラ） | B22: 23年度1大会あたり+（交通費20,000円＊5人） | D22: =350000+100000 -> 450000 | E22: =350000+100000 -> 450000 | F22: =350000+100000 -> 450000
A23: 人件費（運営スタッフ） | B23: 20人想定（外部13人＋7人）交通費含む | C23: 30000 | D23: =E23 -> 600000 | E23: =C23*20 -> 600000 | F23: =E23 -> 600000
A24: メダルトロフィー代 | B24: 23年度3大会仕入れを/3 | D24: 200000 | E24: 200000 | F24: 200000
A25: 会場費 | B25: 23年度参考 | D25: 1600000 | E25: 1600000 | F25: 1600000
A26: 備品消耗品費 | B26: 23年度参考（トランシーバー20,000円、リストバンド等50,000円） | D26: 65000 | E26: 65000 | F26: 65000
A27: 運搬費 | B27: 荷物集荷（往復） | D27: 30000 | E27: 30000 | F27: 30000
A28: 旅費交通費 | B28: 下見等（往復20,000＊2人）＋宿泊費（23年大阪参考：140,000円） | D28: =40000+140000 -> 180000 | E28: =40000+140000 -> 180000 | F28: =40000+140000 -> 180000
A29: 打ち上げ代 | B29: 審査員ご飯、打ち上げあり | D29: 30000 | E29: 30000 | F29: 30000
A30: 通信費 | D30: 50000 | E30: 50000 | F30: 50000
A31: スタッフTシャツ代
A32: 経費合計 | D32: =SUM(D13:D31) -> 4466316.3 | E32: =SUM(E13:E31) -> 4539645.4 | F32: =SUM(F13:F31) -> 4546974.4
A33: 利益合計 | D33: =D11-D32 -> 726691.71 | E33: =E11-E32 -> 1951614.6 | F33: =F11-F32 -> 3242537.6
A34: 利益率 | D34: =D33/D11 -> 0.13993657 | E34: =E33/E11 -> 0.30065267 | F34: =F33/F11 -> 0.41626967

Sheet SFF④（青葉の森公園芸術文化ホール） 
A1: 項目 | B1: 設定 | C1: 単価 | E1: 8/11 千葉 青葉の森公園芸術文化ホール
A2: 売上 | D2: 売上80％ | E2: 前年度参考予想 | F2: 売上120％ | G2: 実数値
A3: 出場費 | B3: 180~220想定のため、200人と仮定 | C3: 5000 | D3: =E3*0.8 -> 800000 | E3: =200*C3 -> 1000000 | F3: =E3*1.2 -> 1200000 | G3: =C3*187 -> 935000
A4: 客席代 | B4: 1,000席内訳：S163席、A376席、B310席の７割想定 価格：S7,000円、A6,000円、B5,000円 | C4: 5500 | D4: =E4*0.8 -> 3047352 | E4: =7700*163*0.7+6600*376*0.7+5500*310*0.7 -> 3809190 | F4: =E4*1.2 -> 4571028 | G4: =7700*163+6600*358+5500*222 -> 4838900
A5: バックサポート代 | B5: 出場者40％想定 | C5: 3300 | D5: =E5*0.8 -> 211200 | E5: =200*0.4*C5 -> 264000 | F5: =E5*1.2 -> 316800 | G5: =C5*140 -> 462000
A6: カラーリング代 | B6: 出場者40%人想定(23年度Tokyo大会参考) 25%フィー | C6: 11000 | D6: =E6*0.8 -> 176000 | E6: =200*0.4*C6*0.25 -> 220000 | F6: =E6*1.2 -> 264000 | G6: 84288
A7: アパレル売上 | B7: 23年度Tokyo大会参考(10%は会場支払のため９割で計算) | D7: =E7*0.8 -> 144000 | E7: =200000*0.9 -> 180000 | F7: =E7*1.2 -> 216000
A8: 写真売上 | B8: 23年度Tokyo大会参考 | D8: =E8*0.8 -> 376000 | E8: 470000 | F8: =E8*1.2 -> 564000 | G8: 322000
A9: 動画販売 | D9: =E9*0.8 -> 120000 | E9: 150000 | F9: =E9*1.2 -> 180000
A10: 協賛金 | D10: 1000000 | E10: 1000000 | F10: 1600000 | G10: ='協賛金計算'!I14 -> 950000
A11: 売上合計 | D11: =SUM(D3:D10) -> 5874552 | E11: =SUM(E3:E10) -> 7093190 | F11: =SUM(F3:F10) -> 8911828 | G11: =SUM(G3:G10) -> 7592188
A12: 経費
A13: 出場チケット手数料（3.6%) | D13: =D3*0.036 -> 28800 | E13: =E3*0.036 -> 36000 | F13: =F3*0.036 -> 43200
A14: 客席チケット手数料（3.6%) | D14: =D4*0.036 -> 109704.67 | E14: =E4*0.036 -> 137130.84 | F14: =F4*0.036 -> 164557.01
A15: バックサポートチケット手数料（3.6%) | D15: =D5*0.036 -> 7603.2 | E15: =E5*0.036 -> 9504 | F15: =F5*0.036 -> 11404.8
A16: カラーリングチケット手数料（3.2%） | B16: 出場者40％想定＊3.2% | C16: 5000 | E16: 0
A17: 動画手数料（3.6%） | D17: =D9*0.036 -> 4320 | E17: =E9*0.036 -> 5400 | F17: =F9*0.036 -> 6480
A18: アパレル仕入れ | B18: 23年度3大会アパレル仕入れを/3 | D18: 100000 | E18: 100000 | F18: 100000
A19: 演出費 | B19: 2/17見積（舞台監督費用含む）【千葉】株式会社Shape Fit御中_ShapeFitFestival千葉大会 青葉の森公園芸術文化ホール_見積書_Q-00000000.pdf | D19: 867900 | E19: 867900 | F19: 867900
A20: 人件費（審査員） | B20: 5名 | C20: 10000 | D20: 50000 | E20: =C20*5 -> 50000 | F20: 50000 | G20: =15000*5 -> 75000
A21: 人件費（MC） | B21: おのっち（3万＋交通費） | E21: 33000
A22: 人件費（カメラ） | B22: 23年度1大会あたり | D22: =E22 -> 350000 | E22: 350000 | F22: =E22 -> 350000
A23: 人件費（運営スタッフ） | B23: 25人想定（東京大会最大30人弱のため） | C23: 9000 | D23: 225000 | E23: =C23*25 -> 225000 | F23: 225000
A24: メダルトロフィー代 | B24: 23年度3大会仕入れを/3 | D24: 200000 | E24: 200000 | F24: 200000
A25: 会場費 | B25: 23年度参考 | D25: =E25 -> 650000 | E25: 650000 | F25: =E25 -> 650000
A26: 備品消耗品費 | B26: 23年度参考（トランシーバー20,000円、リストバンド等50,000円） | D26: 65000 | E26: 65000 | F26: 65000
A27: 運搬費 | B27: 荷物集荷（往復） | D27: 30000 | E27: 30000 | F27: 30000
A28: 旅費交通費 | B28: 下見等（往復2,000＊6人） | D28: 12000 | E28: 12000 | F28: 12000
A29: 打ち上げ代 | B29: 審査員ご飯、打ち上げあり | D29: 30000 | E29: 30000 | F29: 30000
A30: 通信費 | D30: 50000 | E30: 50000 | F30: 50000
A31: スタッフTシャツ代
A32: 経費合計 | D32: =SUM(D13:D31) -> 2780327.9 | E32: =SUM(E13:E31) -> 2850934.8 | F32: =SUM(F13:F31) -> 2855541.8
A33: 利益合計 | D33: =D11-D32 -> 3094224.1 | E33: =E11-E32 -> 4242255.2 | F33: =F11-F32 -> 6056286.2
A34: 利益率 | D34: =D33/D11 -> 0.52671661 | E34: =E33/E11 -> 0.59807437 | F34: =F33/F11 -> 0.67957844

Sheet SFF⑤（松田町生涯学習センター） 
A1: 項目 | B1: 設定 | C1: 単価 | E1: 神奈川大会
A2: 売上 | D2: 売上80％ | E2: 前年度参考予想 | F2: 売上120％ | G2: 実数値
A3: 出場費 | B3: 180~220想定のため、200人と仮定 | C3: 5000 | D3: =E3*0.8 -> 800000 | E3: =200*C3 -> 1000000 | F3: =E3*1.2 -> 1200000 | G3: =C3*304 -> 1520000
A4: 客席代 | B4: 1,000席内訳：S146席、A510席、B326席の７割想定 価格：S7,000円、A6,000円、B5,000円 | C4: 5500 | D4: =E4*0.8 -> 3518592 | E4: =7700*146*0.7+6600*510*0.7+5500*326*0.7 -> 4398240 | F4: =E4*1.2 -> 5277888 | G4: =7700*157+6600*503+5500*322 -> 6299700
A5: バックサポート代 | B5: 出場者40％想定 | C5: 3300 | D5: =E5*0.8 -> 211200 | E5: =200*0.4*C5 -> 264000 | F5: =E5*1.2 -> 316800 | G5: =C5*197 -> 650100
A6: カラーリング代 | B6: 出場者40%人想定(23年度Tokyo大会参考) 25%フィー | C6: 11000 | D6: =E6*0.8 -> 176000 | E6: =200*0.4*C6*0.25 -> 220000 | F6: =E6*1.2 -> 264000
A7: アパレル売上 | B7: 23年度Tokyo大会参考(10%は会場支払のため９割で計算) | D7: =E7*0.8 -> 144000 | E7: =200000*0.9 -> 180000 | F7: =E7*1.2 -> 216000
A8: 写真売上 | B8: 23年度Tokyo大会参考 | D8: =E8*0.8 -> 376000 | E8: 470000 | F8: =E8*1.2 -> 564000
A9: 動画販売 | D9: =E9*0.8 -> 120000 | E9: 150000 | F9: =E9*1.2 -> 180000
A10: 協賛金 | D10: 1200000 | E10: 1200000 | F10: 1950000 | G10: ='協賛金計算'!I15 -> 2005000
A11: 売上合計 | D11: =SUM(D3:D10) -> 6545792 | E11: =SUM(E3:E10) -> 7882240 | F11: =SUM(F3:F10) -> 9968688
A12: 経費
A13: 出場チケット手数料（3.6%) | D13: =D3*0.036 -> 28800 | E13: =E3*0.036 -> 36000 | F13: =F3*0.036 -> 43200
A14: 客席チケット手数料（3.6%) | D14: =D4*0.036 -> 126669.31 | E14: =E4*0.036 -> 158336.64 | F14: =F4*0.036 -> 190003.97
A15: バックサポートチケット手数料（3.6%) | D15: =D5*0.036 -> 7603.2 | E15: =E5*0.036 -> 9504 | F15: =F5*0.036 -> 11404.8
A16: カラーリングチケット手数料（3.2%） | B16: 出場者40％想定＊3.2% | C16: 5000 | E16: 0
A17: 動画手数料（3.6%） | D17: =D9*0.036 -> 4320 | E17: =E9*0.036 -> 5400 | F17: =F9*0.036 -> 6480
A18: アパレル仕入れ | B18: 23年度3大会アパレル仕入れを/3 | D18: 500000 | E18: 500000 | F18: 500000 | G18: =15000*3+10000*2 -> 65000
A19: 演出費 | B19: 2/17見積（舞台監督費用含む）【神奈川】株式会社Shape Fit御中_ShapeFitFestival神奈川大会 松田町生涯学習センター_見積書_Q-0000000010.pdf | D19: 1118700 | E19: 1118700 | F19: 1118700
A20: 人件費（審査員） | B20: 5名 | C20: 10000 | D20: 50000 | E20: =C20*5 -> 50000 | F20: 50000
A21: 人件費（MC） | B21: えいみーさん（5万円＋交通費） | E21: 55000
A22: 人件費（カメラ） | B22: 23年度1大会あたり | D22: =E22 -> 350000 | E22: 350000 | F22: =E22 -> 350000
A23: 人件費（運営スタッフ） | B23: 25人想定（東京大会最大30人弱のため） | C23: 9000 | D23: 225000 | E23: =C23*25 -> 225000 | F23: 225000
A24: メダルトロフィー代 | B24: 23年度3大会仕入れを/3 | D24: 200000 | E24: 200000 | F24: 200000
A25: 会場費 | B25: 23年度参考 | D25: =E25 -> 650000 | E25: 650000 | F25: =E25 -> 650000
A26: 備品消耗品費 | B26: 23年度参考（トランシーバー20,000円、リストバンド等50,000円） | D26: 65000 | E26: 65000 | F26: 65000
A27: 運搬費 | B27: 荷物集荷（往復） | D27: 30000 | E27: 30000 | F27: 30000
A28: 旅費交通費 | B28: 下見等（往復2,000＊6人） | D28: 12000 | E28: 12000 | F28: 12000
A29: 打ち上げ代 | B29: 審査員ご飯、打ち上げあり | D29: 30000 | E29: 30000 | F29: 30000
A30: 通信費 | D30: 50000 | E30: 50000 | F30: 50000
A31: スタッフTシャツ代
A32: 経費合計 | D32: =SUM(D13:D31) -> 3448092.5 | E32: =SUM(E13:E31) -> 3544940.6 | F32: =SUM(F13:F31) -> 3531788.8
A33: 利益合計 | D33: =D11-D32 -> 3097699.5 | E33: =E11-E32 -> 4337299.4 | F33: =F11-F32 -> 6436899.2
A34: 利益率 | D34: =D33/D11 -> 0.47323525 | E34: =E33/E11 -> 0.55026228 | F34: =F33/F11 -> 0.64571178

Sheet SFF⑥（ALL草加市文化会館）
A1: 項目 | B1: 設定 | C1: 単価 | E1: 全国大会
A2: 売上 | D2: 売上80％ | E2: 前年度参考予想 | F2: 売上120％ | G2: 実数値
A3: 出場費 | B3: 180~220想定のため、200人と仮定 | C3: 8000 | D3: =E3*0.8 -> 640000 | E3: =100*C3 -> 800000 | F3: =E3*1.2 -> 960000
A4: 客席代 | B4: 1,000席内訳：S162席、A389席、B644席の７割想定 価格：S7,000円、A6,000円、B5,000円 | C4: 5500 | D4: =E4*0.8 -> 4119808 | E4: =7700*162*0.7+6600*389*0.7+5500*644*0.7 -> 5149760 | F4: =E4*1.2 -> 6179712 | G4: =7700*162+6600*389+5500*644 -> 7356800
A5: バックサポート代 | B5: 出場者40％想定 | C5: 3300 | D5: =E5*0.8 -> 105600 | E5: =100*0.4*C5 -> 132000 | F5: =E5*1.2 -> 158400
A6: カラーリング代 | B6: 出場者40%人想定(23年度Tokyo大会参考) 25%フィー | C6: 11000 | D6: =E6*0.8 -> 176000 | E6: =200*0.4*C6*0.25 -> 220000 | F6: =E6*1.2 -> 264000
A7: アパレル売上 | B7: 23年度Tokyo大会参考 | D7: =E7*0.8 -> 160000 | E7: 200000 | F7: =E7*1.2 -> 240000
A8: 写真売上 | B8: 23年度Tokyo大会参考 | D8: =E8*0.8 -> 376000 | E8: 470000 | F8: =E8*1.2 -> 564000
A9: 動画販売 | D9: =E9*0.8 -> 120000 | E9: 150000 | F9: =E9*1.2 -> 180000
A10: 協賛金 | D10: 3270000 | E10: 3270000 | F10: 3900000 | G10: ='協賛金計算'!I16 -> 4260000 | J10: 1000000 | K10: 1000000 | L10: 1600000 | M10: 協賛金 | P10: 1000000 | Q10: 1000000 | R10: 1600000 | S10: 協賛金 | V10: 1000000 | W10: 1000000 | X10: 1600000 | Y10: 協賛金 | AB10: 1000000 | AC10: 1000000 | AD10: 1600000 | AE10: 協賛金 | AH10: 1000000 | AI10: 1000000 | AJ10: 1600000
A11: 売上合計 | D11: =SUM(D3:D10) -> 8967408 | E11: =SUM(E3:E10) -> 10391760 | F11: =SUM(F3:F10) -> 12446112
A12: 経費
A13: 出場チケット手数料（3.6%) | D13: =D3*0.036 -> 23040 | E13: =E3*0.036 -> 28800 | F13: =F3*0.036 -> 34560
A14: 客席チケット手数料（3.6%) | D14: =D4*0.036 -> 148313.09 | E14: =E4*0.036 -> 185391.36 | F14: =F4*0.036 -> 222469.63
A15: バックサポートチケット手数料（3.6%) | D15: =D5*0.036 -> 3801.6 | E15: =E5*0.036 -> 4752 | F15: =F5*0.036 -> 5702.4
A16: カラーリングチケット手数料（3.2%） | B16: 出場者40％想定＊3.2% | C16: 5000 | E16: 0
A17: 動画手数料（3.6%） | D17: =D9*0.036 -> 4320 | E17: =E9*0.036 -> 5400 | F17: =F9*0.036 -> 6480
A18: アパレル仕入れ | B18: 23年度3大会アパレル仕入れを/3 | D18: 500000 | E18: 500000 | F18: 500000
A19: 演出費 | B19: 2/17見積（舞台監督費用含む）【全国（埼玉）】株式会社Shape Fit御中_ShapeFitFestival全国大会 草加市文化会館_見積書_Q-0000000008.pdf | D19: 2901800 | E19: 2901800 | F19: 2901800
A20: 人件費（審査員） | B20: 5名 | C20: 10000 | D20: 50000 | E20: =C20*5 -> 50000 | F20: 50000
A21: 人件費（MC） | B21: ぷり（３万＋交通費） | E21: 60000
A22: 人件費（カメラ） | B22: 23年度1大会あたり | D22: =E22 -> 350000 | E22: 350000 | F22: =E22 -> 350000 | G22: =15000*5 -> 75000
A23: 人件費（運営スタッフ） | B23: 25人想定（東京大会最大30人弱のため） | C23: 9000 | D23: 225000 | E23: =C23*25 -> 225000 | F23: 225000
A24: メダルトロフィー代 | B24: 23年度3大会仕入れを/3 | D24: 200000 | E24: 200000 | F24: 200000
A25: 会場費 | B25: すでに301,510円支払(23年度参考) | D25: 1600000 | E25: 1600000 | F25: 1600000
A26: 備品消耗品費 | B26: 23年度参考（トランシーバー20,000円、リストバンド等50,000円） | D26: 65000 | E26: 65000 | F26: 65000
A27: 運搬費 | B27: 荷物集荷（往復） | D27: 30000 | E27: 30000 | F27: 30000
A28: 旅費交通費 | B28: 下見等（往復2,000＊6人） | D28: 12000 | E28: 12000 | F28: 12000
A29: 打ち上げ代 | B29: 審査員ご飯、打ち上げあり | D29: 30000 | E29: 30000 | F29: 30000
A30: 通信費 | D30: 50000 | E30: 50000 | F30: 50000
A31: スタッフTシャツ代
A32: 経費合計 | D32: =SUM(D13:D31) -> 6193274.7 | E32: =SUM(E13:E31) -> 6298143.4 | F32: =SUM(F13:F31) -> 6283012
A33: 利益合計 | D33: =D11-D32 -> 2774133.3 | E33: =E11-E32 -> 4093616.6 | F33: =F11-F32 -> 6163100
A34: 利益率 | D34: =D33/D11 -> 0.30935732 | E34: =E33/E11 -> 0.3939291 | F34: =F33/F11 -> 0.49518275

Sheet 購入品リスト
B2: 日付 | C2: 購入品 | D2: 大会名 | E2: 金額（税込）
B3: 45689 | C3: 説明会用スリッパ | D3: 全体 | E3: 3000
B4: 45707 | C4: WTBメダルサンプル | D4: 全体 | E4: 16234
B5: 45707 | C5: WTBメダルサンプル | D5: 全体 | E5: 20658
B6: 45716 | C6: バッジ番号修正 | D6: 全体 | E6: 17408
B7: 45733 | C7: 銀銅メダル | D7: 全体 | E7: 30275
B8: 45735 | C8: 交通費 神奈川メンバー | D8: 福岡 | E8: 131040
B9: 45735 | C9: 交通保険 神奈川メンバー | D9: 福岡 | E9: 5355
B10: 45735 | C10: 金メダル | D10: 全体 | E10: 321900
B11: 45735 | C11: カメラ機材 | D11: 全体 | E11: 680702
B12: 45739 | C12: 予選用バッジ | D12: 全体 | E12: 237270
B13: 45744 | C13: カメラ機材（テザーツール） | D13: 全体 | E13: 9460
B14: 45757 | C14: リストバンド、45L袋 | D14: 全体 | E14: ￥24,813
B15: 45772 | C15: カメラマン指導 | D15: 全体 | E15: 165000
C26: スタンプラリーシール | E26: 250000

Sheet 協賛金計算
A1: ｃ
C2: TOP | D2: DIAMOND | E2: PLATINUM | F2: GOLD | G2: SILVER | H2: BRONZE
A3: 東京大会 | B3: AMBiQUE | C3: VEATM | E3: VOLIX | F3: 極洋 | G3: 株式会社ALAWAY ステディジャパン issin
A4: 福岡大会 | B4: AMBiQUE | C4: ペコダック | E4: VOLIX
A5: 大阪大会OK | B5: AMBiQUE | C5: VOLIX | E5: 痛みのクリニック
A6: 千葉大会 | B6: AMBiQUE | C6: VEATM
A7: 神奈川大会 | B7: AMBiQUE | C7: VEATM | D7: VITAS | E7: ペコダック トラストワーク
A8: ALL | C8: AMBiQUE | D8: VITAS | E8: ペコダック Power LIfe | F8: 極洋
C10: TOP | D10: DIAMOND | E10: PLATINUM | F10: GOLD | G10: SILVER | H10: BRONZE
A11: 東京大会 | C11: 1200000 | D11: 500000 | E11: =250000*0.9 -> 225000 | F11: 100000 | G11: 50000 | H11: 30000 | I11: =C11+F11+E11 -> 1525000
A12: 福岡大会 | C12: 500000 | D12: 250000 | E12: =150000*0.9 -> 135000 | F12: 100000 | G12: 50000 | H12: 30000 | I12: =C12+E12+G12 -> 685000
A13: 大阪大会OK | C13: 1000000 | D13: 400000 | E13: 200000 | F13: 100000 | G13: 50000 | H13: 30000 | I13: =C13+E13+G13 -> 1250000
A14: 千葉大会 | C14: =1000000*0.9 -> 900000 | D14: 400000 | E14: 200000 | F14: 100000 | G14: 50000 | H14: 30000 | I14: =C14+G14 -> 950000
A15: 神奈川大会 | C15: =1200000*0.9 -> 1080000 | D15: =500000*0.9 -> 450000 | E15: =250000*0.9+250000 -> 475000 | F15: 100000 | G15: 50000 | H15: 30000 | I15: =C15+E15+D15 -> 2005000
A16: ALL | C16: 3000000 | D16: 600000 | E16: =300000*0.9+300000 -> 570000 | F16: =100000*0.9 -> 90000 | G16: 50000 | H16: 30000 | I16: =C16+E16+F16+D16 -> 4260000
I17: =SUM(I11:I16) -> 10675000
A18: VEATM | B18: =C11+C14+C15 -> 3180000
A19: AMBiQUE | B19: =C16 -> 3000000
A20: ペコダック | B20: =C12+250000*0.9+300000*0.9 -> 995000
A21: VOLIX | B21: =C13+(E11+E12) -> 1360000
A22: 痛みのクリニック | B22: =E13 -> 200000
A23: トラストワーク | B23: =250000 -> 250000
A24: 極洋 | B24: =F11+F16 -> 190000
A25: VITAS | B25: =D15+D16 -> 1050000
A26: ステディジャパン | B26: =G14 -> 50000
A27: issin | B27: =G12 -> 50000
A28: Power LIfe | B28: =300000 -> 300000
A29: 中村さん | B29: =G13 -> 50000
B30: =SUM(B18:B29) -> 10675000
