Workbook

Sheet ダッシュボード
A1: SFF大会 収益シミュレーション ダッシュボード
A3: 【目標設定】
A4: 売上目標（2大会合計） | C4: 51653879 | D4: ※前年比120%
A5: 限界利益率目標 | C5: 0.5
A7: 【KPIサマリー（2大会合計）】
A8: 項目 | B8: PJT1 | C8: PJT2 | D8: 合計 | E8: 目標 | F8: 達成率
A9: 売上合計 | B9: ='PJT1_収支'!B4 -> 18660000 | C9: ='PJT2_収支'!B4 -> 18660000 | D9: =B9+C9 -> 37320000 | E9: =C4 -> 51653879 | F9: =IF(E9=0,0,D9/E9) -> 0.7225014
A10: 変動費合計 | B10: ='PJT1_収支'!B5 -> 9071760 | C10: ='PJT2_収支'!B5 -> 9071760 | D10: =B10+C10 -> 18143520 | E10: - | F10: -
A11: 限界利益 | B11: ='PJT1_収支'!B6 -> 9588240 | C11: ='PJT2_収支'!B6 -> 9588240 | D11: =B11+C11 -> 19176480 | E11: =D9*C5 -> 18660000 | F11: =IF(E11=0,0,D11/E11) -> 1.0276785
A12: 限界利益率 | B12: ='PJT1_収支'!B7 -> 0.51383923 | C12: ='PJT2_収支'!B7 -> 0.51383923 | D12: =IF(D9=0,0,D11/D9) -> 0.51383923 | E12: =C5 -> 0.5 | F12: =IF(E12=0,0,D12/E12) -> 1.0276785
A14: 【達成判定】
A15: 売上目標 | B15: =IF(D9>=C4,"✓ 達成","✗ 未達") -> ✗ 未達
A16: 利益率目標 | B16: =IF(D12>=C5,"✓ 達成","✗ 未達") -> ✓ 達成
A18: 【大会別 収益内訳】
A19: 収益項目 | B19: PJT1 | C19: PJT2 | D19: 合計
A20: 選手売上 | B20: ='PJT1_収支'!B11 -> 2960000 | C20: ='PJT2_収支'!B11 -> 2960000 | D20: =B20+C20 -> 5920000
A21: 観客売上 | B21: ='PJT1_収支'!B12 -> 11400000 | C21: ='PJT2_収支'!B12 -> 11400000 | D21: =B21+C21 -> 22800000
A22: スポンサー売上 | B22: ='PJT1_収支'!B13 -> 1900000 | C22: ='PJT2_収支'!B13 -> 1900000 | D22: =B22+C22 -> 3800000
A23: 付帯収入 | B23: ='PJT1_収支'!B14 -> 2400000 | C23: ='PJT2_収支'!B14 -> 2400000 | D23: =B23+C23 -> 4800000

Sheet PJT1_入力
A1: PJT1（パープルホール）入力シート
A3: 【選手】
A4: カテゴリ | B4: 単価 | C4: 人数 | D4: 売上
A5: 一般 | B5: 15000 | C5: 100 | D5: =B5*C5 -> 1500000
A6: Wエントリー | B6: 8000 | C6: 50 | D6: =B6*C6 -> 400000
A7: 学生/新人 | B7: 8000 | C7: 50 | D7: =B7*C7 -> 400000
A8: バックサポート | B8: 3300 | C8: 150 | D8: =B8*C8 -> 495000
A9: ステージパートナー | B9: 3300 | C9: 50 | D9: =B9*C9 -> 165000
A10: 選手売上 小計 | D10: =SUM(D5:D9) -> 2960000
A12: 【観客】
A13: 席種 | B13: 単価 | C13: キャパ | D13: 販売数 | E13: 売上 | F13: 充足率
A14: VIP席 | B14: 50000 | C14: 30 | D14: 30 | E14: =B14*D14 -> 1500000 | F14: =IF(C14=0,0,D14/C14) -> 1
A15: S席 | B15: 12000 | C15: 300 | D15: 300 | E15: =B15*D15 -> 3600000 | F15: =IF(C15=0,0,D15/C15) -> 1
A16: A席 | B16: 8000 | C16: 600 | D16: 600 | E16: =B16*D16 -> 4800000 | F16: =IF(C16=0,0,D16/C16) -> 1
A17: B席 | B17: 5000 | C17: 300 | D17: 300 | E17: =B17*D17 -> 1500000 | F17: =IF(C17=0,0,D17/C17) -> 1
A18: 観客売上 小計 | C18: =SUM(C14:C17) -> 1230 | D18: =SUM(D14:D17) -> 1230 | E18: =SUM(E14:E17) -> 11400000 | F18: =IF(C18=0,0,D18/C18) -> 1
A20: 【スポンサー】
A21: プラン | B21: 単価 | C21: 社数 | D21: 売上
A22: TOPパートナー | B22: 5000000 | C22: 0 | D22: =B22*C22 -> 0
A23: DIAMOND | B23: 700000 | C23: 1 | D23: =B23*C23 -> 700000
A24: PLATINUM | B24: 300000 | C24: 4 | D24: =B24*C24 -> 1200000
A25: GOLD/物品 | B25: 100000 | C25: 0 | D25: =B25*C25 -> 0
A26: スポンサー売上 小計 | D26: =SUM(D22:D25) -> 1900000
A28: 【付帯収入】
A29: 項目 | B29: 売上
A30: 物販売上 | B30: 800000
A31: フォトレコ | B31: 1000000
A32: 動画販売 | B32: 400000
A33: カラーリング | B33: 200000
A34: 付帯収入 小計 | B34: =SUM(B30:B33) -> 2400000

Sheet PJT2_入力
A1: PJT2（ひらしん）入力シート
A3: 【選手】
A4: カテゴリ | B4: 単価 | C4: 人数 | D4: 売上
A5: 一般 | B5: 15000 | C5: 100 | D5: =B5*C5 -> 1500000
A6: Wエントリー | B6: 8000 | C6: 50 | D6: =B6*C6 -> 400000
A7: 学生/新人 | B7: 8000 | C7: 50 | D7: =B7*C7 -> 400000
A8: バックサポート | B8: 3300 | C8: 150 | D8: =B8*C8 -> 495000
A9: ステージパートナー | B9: 3300 | C9: 50 | D9: =B9*C9 -> 165000
A10: 選手売上 小計 | D10: =SUM(D5:D9) -> 2960000
A12: 【観客】
A13: 席種 | B13: 単価 | C13: キャパ | D13: 販売数 | E13: 売上 | F13: 充足率
A14: VIP席 | B14: 50000 | C14: 30 | D14: 30 | E14: =B14*D14 -> 1500000 | F14: =IF(C14=0,0,D14/C14) -> 1
A15: S席 | B15: 12000 | C15: 300 | D15: 300 | E15: =B15*D15 -> 3600000 | F15: =IF(C15=0,0,D15/C15) -> 1
A16: A席 | B16: 8000 | C16: 600 | D16: 600 | E16: =B16*D16 -> 4800000 | F16: =IF(C16=0,0,D16/C16) -> 1
A17: B席 | B17: 5000 | C17: 300 | D17: 300 | E17: =B17*D17 -> 1500000 | F17: =IF(C17=0,0,D17/C17) -> 1
A18: 観客売上 小計 | C18: =SUM(C14:C17) -> 1230 | D18: =SUM(D14:D17) -> 1230 | E18: =SUM(E14:E17) -> 11400000 | F18: =IF(C18=0,0,D18/C18) -> 1
A20: 【スポンサー】
A21: プラン | B21: 単価 | C21: 社数 | D21: 売上
A22: TOPパートナー | B22: 5000000 | C22: 0 | D22: =B22*C22 -> 0
A23: DIAMOND | B23: 700000 | C23: 1 | D23: =B23*C23 -> 700000
A24: PLATINUM | B24: 300000 | C24: 4 | D24: =B24*C24 -> 1200000
A25: GOLD/物品 | B25: 100000 | C25: 0 | D25: =B25*C25 -> 0
A26: スポンサー売上 小計 | D26: =SUM(D22:D25) -> 1900000
A28: 【付帯収入】
A29: 項目 | B29: 売上
A30: 物販売上 | B30: 800000
A31: フォトレコ | B31: 1000000
A32: 動画販売 | B32: 400000
A33: カラーリング | B33: 200000
A34: 付帯収入 小計 | B34: =SUM(B30:B33) -> 2400000

Sheet コスト
A1: コスト入力シート
A3: 【PJT1 コスト】
A4: 費目 | B4: 予算(円) | C4: 備考
A5: 会場費・設営費 | B5: 4000000 | C5: 2日分＋設営費
A6: 音響・照明・演出 | B6: 2500000 | C6: クオリティ維持
A7: 人件費・運営費（業務委託） | B7: 300000 | C7: スタッフ・警備
A8: 制作物・広報費 | B8: 1000000 | C8: パンフ・Web制作
A9: 決済手数料（3.6%） | B9: =('PJT1_入力'!D10+'PJT1_入力'!E18+'PJT1_入力'!D26+'PJT1_入力'!B34)*0.036 -> 671760 | C9: 売上の3.6%
A10: 予備費 | B10: 600000 | C10: リスクヘッジ
A11: 社内人件費 | B11: 0 | C11: ※項目のみ（初期値0）
A12: PJT1 コスト合計 | B12: =SUM(B5:B11) -> 9071760
A14: 【PJT2 コスト】
A15: 費目 | B15: 予算(円) | C15: 備考
A16: 会場費・設営費 | B16: 4000000 | C16: 2日分＋設営費
A17: 音響・照明・演出 | B17: 2500000 | C17: クオリティ維持
A18: 人件費・運営費（業務委託） | B18: 300000 | C18: スタッフ・警備
A19: 制作物・広報費 | B19: 1000000 | C19: パンフ・Web制作
A20: 決済手数料（3.6%） | B20: =('PJT2_入力'!D10+'PJT2_入力'!E18+'PJT2_入力'!D26+'PJT2_入力'!B34)*0.036 -> 671760 | C20: 売上の3.6%
A21: 予備費 | B21: 600000 | C21: リスクヘッジ
A22: 社内人件費 | B22: 0 | C22: ※項目のみ（初期値0）
A23: PJT2 コスト合計 | B23: =SUM(B16:B22) -> 9071760

Sheet PJT1_収支
A1: PJT1（パープルホール）収支計算
A3: 項目 | B3: 金額
A4: 売上合計 | B4: =B11+B12+B13+B14 -> 18660000
A5: 変動費合計 | B5: ='コスト'!B12 -> 9071760
A6: 限界利益 | B6: =B4-B5 -> 9588240
A7: 限界利益率 | B7: =IF(B4=0,0,B6/B4) -> 0.51383923
A9: 【売上内訳】
A10: カテゴリ | B10: 金額 | C10: 構成比
A11: 選手売上 | B11: ='PJT1_入力'!D10 -> 2960000 | C11: =IF($B$4=0,0,B11/$B$4) -> 0.15862808
A12: 観客売上 | B12: ='PJT1_入力'!E18 -> 11400000 | C12: =IF($B$4=0,0,B12/$B$4) -> 0.61093248
A13: スポンサー売上 | B13: ='PJT1_入力'!D26 -> 1900000 | C13: =IF($B$4=0,0,B13/$B$4) -> 0.10182208
A14: 付帯収入 | B14: ='PJT1_入力'!B34 -> 2400000 | C14: =IF($B$4=0,0,B14/$B$4) -> 0.12861736

Sheet PJT2_収支
A1: PJT2（ひらしん）収支計算
A3: 項目 | B3: 金額
A4: 売上合計 | B4: =B11+B12+B13+B14 -> 18660000
A5: 変動費合計 | B5: ='コスト'!B23 -> 9071760
A6: 限界利益 | B6: =B4-B5 -> 9588240
A7: 限界利益率 | B7: =IF(B4=0,0,B6/B4) -> 0.51383923
A9: 【売上内訳】
A10: カテゴリ | B10: 金額 | C10: 構成比
A11: 選手売上 | B11: ='PJT2_入力'!D10 -> 2960000 | C11: =IF($B$4=0,0,B11/$B$4) -> 0.15862808
A12: 観客売上 | B12: ='PJT2_入力'!E18 -> 11400000 | C12: =IF($B$4=0,0,B12/$B$4) -> 0.61093248
A13: スポンサー売上 | B13: ='PJT2_入力'!D26 -> 1900000 | C13: =IF($B$4=0,0,B13/$B$4) -> 0.10182208
A14: 付帯収入 | B14: ='PJT2_入力'!B34 -> 2400000 | C14: =IF($B$4=0,0,B14/$B$4) -> 0.12861736
